[{"date": "2016-12-31", "lng": -74.00788, "lat": 40.711533, "zipCode": 10038, "severityType": 1, "year": 2016}, {"date": "2016-12-23", "lng": -74.00729, "lat": 40.7087, "zipCode": 10038, "severityType": 0, "year": 2016}, {"date": "2016-12-21", "lng": -73.998184, "lat": 40.71329, "zipCode": 10038, "severityType": 0, "year": 2016}, {"date": "2016-12-20", "lng": -74.001144, "lat": 40.710175, "zipCode": 10038, "severityType": 0, "year": 2016}, {"date": "2016-12-20", "lng": -74.004456, "lat": 40.710007, "zipCode": 10038, "severityType": 1, "year": 2016}, {"date": "2016-12-20", "lng": -74.00166999999999, "lat": 40.709503000000005, "zipCode": 10038, "severityType": 0, "year": 2016}, {"date": "2016-12-19", "lng": -73.99633, "lat": 40.70991, "zipCode": 10038, "severityType": 0, "year": 2016}, {"date": "2016-12-17", "lng": -74.00635, "lat": 40.706394, "zipCode": 10038, "severityType": 0, "year": 2016}, {"date": "2016-12-16", "lng": -74.00647, "lat": 40.70817, "zipCode": 10038, "severityType": 0, "year": 2016}, {"date": "2016-12-15", "lng": -74.00166999999999, "lat": 40.709503000000005, "zipCode": 10038, "severityType": 0, "year": 2016}, {"date": "2016-12-14", "lng": -74.001144, "lat": 40.710175, "zipCode": 10038, "severityType": 0, "year": 2016}, {"date": "2016-12-13", "lng": -74.00303000000001, "lat": 40.706326000000004, "zipCode": 10038, "severityType": 0, "year": 2016}, {"date": "2016-12-11", "lng": -74.00495, "lat": 40.70864, "zipCode": 10038, "severityType": 1, "year": 2016}, {"date": "2016-12-09", "lng": -74.00501, "lat": 40.706852000000005, "zipCode": 10038, "severityType": 0, "year": 2016}, {"date": "2016-12-08", "lng": -74.0009, "lat": 40.712357, "zipCode": 10038, "severityType": 0, "year": 2016}, {"date": "2016-12-08", "lng": -74.004486, "lat": 40.709957, "zipCode": 10038, "severityType": 0, "year": 2016}, {"date": "2016-12-05", "lng": -74.006485, "lat": 40.71123, "zipCode": 10038, "severityType": 0, "year": 2016}, {"date": "2016-12-05", "lng": -74.0061, "lat": 40.711926, "zipCode": 10038, "severityType": 0, "year": 2016}, {"date": "2016-12-05", "lng": -74.00166999999999, "lat": 40.709503000000005, "zipCode": 10038, "severityType": 0, "year": 2016}, {"date": "2016-12-03", "lng": -73.99750999999999, "lat": 40.712013, "zipCode": 10038, "severityType": 0, "year": 2016}, {"date": "2016-11-30", "lng": -74.0009, "lat": 40.712357, "zipCode": 10038, "severityType": 0, "year": 2016}, {"date": "2016-11-30", "lng": -74.00392, "lat": 40.710426, "zipCode": 10038, "severityType": 0, "year": 2016}, {"date": "2016-11-29", "lng": -74.00729, "lat": 40.7087, "zipCode": 10038, "severityType": 0, "year": 2016}, {"date": "2016-11-29", "lng": -74.00729, "lat": 40.7087, "zipCode": 10038, "severityType": 0, "year": 2016}, {"date": "2016-11-29", "lng": -74.00501, "lat": 40.706852000000005, "zipCode": 10038, "severityType": 0, "year": 2016}, {"date": "2016-11-28", "lng": -73.99695600000001, "lat": 40.712070000000004, "zipCode": 10038, "severityType": 0, "year": 2016}, {"date": "2016-11-25", "lng": -74.00426, "lat": 40.710163, "zipCode": 10038, "severityType": 1, "year": 2016}, {"date": "2016-11-23", "lng": -74.00729, "lat": 40.7087, "zipCode": 10038, "severityType": 0, "year": 2016}, {"date": "2016-11-22", "lng": -74.00777, "lat": 40.707657, "zipCode": 10038, "severityType": 0, "year": 2016}, {"date": "2016-11-17", "lng": -74.00166999999999, "lat": 40.709503000000005, "zipCode": 10038, "severityType": 0, "year": 2016}, {"date": "2016-11-17", "lng": -74.00601, "lat": 40.70998, "zipCode": 10038, "severityType": 0, "year": 2016}, {"date": "2016-11-16", "lng": -73.99971, "lat": 40.711777000000005, "zipCode": 10038, "severityType": 0, "year": 2016}, {"date": "2016-11-15", "lng": -74.00194499999999, "lat": 40.708252, "zipCode": 10038, "severityType": 0, "year": 2016}, {"date": "2016-11-14", "lng": -74.00828, "lat": 40.71111, "zipCode": 10038, "severityType": 0, "year": 2016}, {"date": "2016-11-11", "lng": -74.00166999999999, "lat": 40.709503000000005, "zipCode": 10038, "severityType": 0, "year": 2016}, {"date": "2016-11-11", "lng": -74.00775, "lat": 40.71022, "zipCode": 10038, "severityType": 0, "year": 2016}, {"date": "2016-11-08", "lng": -74.00522, "lat": 40.707096, "zipCode": 10038, "severityType": 0, "year": 2016}, {"date": "2016-11-02", "lng": -74.00014, "lat": 40.707912, "zipCode": 10038, "severityType": 0, "year": 2016}, {"date": "2016-11-02", "lng": -74.00166999999999, "lat": 40.709503000000005, "zipCode": 10038, "severityType": 0, "year": 2016}, {"date": "2016-10-31", "lng": -74.00851, "lat": 40.70946, "zipCode": 10038, "severityType": 0, "year": 2016}, {"date": "2016-10-28", "lng": -73.99868000000001, "lat": 40.711876000000004, "zipCode": 10038, "severityType": 0, "year": 2016}, {"date": "2016-10-28", "lng": -74.00052, "lat": 40.710983, "zipCode": 10038, "severityType": 0, "year": 2016}, {"date": "2016-10-26", "lng": -74.00166999999999, "lat": 40.709503000000005, "zipCode": 10038, "severityType": 1, "year": 2016}, {"date": "2016-10-26", "lng": -74.004265, "lat": 40.707336, "zipCode": 10038, "severityType": 0, "year": 2016}, {"date": "2016-10-24", "lng": -74.00251, "lat": 40.708843, "zipCode": 10038, "severityType": 0, "year": 2016}, {"date": "2016-10-24", "lng": -74.006096, "lat": 40.70991, "zipCode": 10038, "severityType": 0, "year": 2016}, {"date": "2016-10-23", "lng": -74.00484, "lat": 40.70966, "zipCode": 10038, "severityType": 0, "year": 2016}, {"date": "2016-10-22", "lng": -74.00376999999999, "lat": 40.705868, "zipCode": 10038, "severityType": 0, "year": 2016}, {"date": "2016-10-21", "lng": -73.99778, "lat": 40.71197, "zipCode": 10038, "severityType": 0, "year": 2016}, {"date": "2016-10-17", "lng": -74.006096, "lat": 40.70991, "zipCode": 10038, "severityType": 0, "year": 2016}, {"date": "2016-10-14", "lng": -73.99875, "lat": 40.712727, "zipCode": 10038, "severityType": 0, "year": 2016}, {"date": "2016-10-14", "lng": -74.00775, "lat": 40.71022, "zipCode": 10038, "severityType": 0, "year": 2016}, {"date": "2016-10-13", "lng": -74.00729, "lat": 40.7087, "zipCode": 10038, "severityType": 0, "year": 2016}, {"date": "2016-10-13", "lng": -74.00910999999999, "lat": 40.710026, "zipCode": 10038, "severityType": 0, "year": 2016}, {"date": "2016-10-13", "lng": -74.0043, "lat": 40.707287, "zipCode": 10038, "severityType": 0, "year": 2016}, {"date": "2016-10-11", "lng": -74.00584, "lat": 40.711655, "zipCode": 10038, "severityType": 0, "year": 2016}, {"date": "2016-10-06", "lng": -74.00644, "lat": 40.709557000000004, "zipCode": 10038, "severityType": 0, "year": 2016}, {"date": "2016-10-05", "lng": -73.998184, "lat": 40.71329, "zipCode": 10038, "severityType": 0, "year": 2016}, {"date": "2016-10-03", "lng": -74.00166999999999, "lat": 40.709503000000005, "zipCode": 10038, "severityType": 0, "year": 2016}, {"date": "2016-10-01", "lng": -74.00774, "lat": 40.711566999999995, "zipCode": 10038, "severityType": 0, "year": 2016}, {"date": "2016-09-23", "lng": -74.005104, "lat": 40.70605, "zipCode": 10038, "severityType": 0, "year": 2016}, {"date": "2016-09-22", "lng": -74.00501, "lat": 40.706852000000005, "zipCode": 10038, "severityType": 0, "year": 2016}, {"date": "2016-09-21", "lng": -74.0072, "lat": 40.7107, "zipCode": 10038, "severityType": 0, "year": 2016}, {"date": "2016-09-18", "lng": -73.998, "lat": 40.712723, "zipCode": 10038, "severityType": 0, "year": 2016}, {"date": "2016-09-17", "lng": -73.99971, "lat": 40.711777000000005, "zipCode": 10038, "severityType": 0, "year": 2016}, {"date": "2016-09-17", "lng": -73.99982, "lat": 40.711655, "zipCode": 10038, "severityType": 0, "year": 2016}, {"date": "2016-09-13", "lng": -73.99679, "lat": 40.71136, "zipCode": 10038, "severityType": 0, "year": 2016}, {"date": "2016-09-13", "lng": -74.006584, "lat": 40.710175, "zipCode": 10038, "severityType": 0, "year": 2016}, {"date": "2016-09-13", "lng": -74.00014, "lat": 40.707912, "zipCode": 10038, "severityType": 0, "year": 2016}, {"date": "2016-09-12", "lng": -73.99695600000001, "lat": 40.712070000000004, "zipCode": 10038, "severityType": 0, "year": 2016}, {"date": "2016-09-10", "lng": -74.006485, "lat": 40.71123, "zipCode": 10038, "severityType": 0, "year": 2016}, {"date": "2016-09-09", "lng": -74.001144, "lat": 40.710175, "zipCode": 10038, "severityType": 0, "year": 2016}, {"date": "2016-09-08", "lng": -74.00194499999999, "lat": 40.708252, "zipCode": 10038, "severityType": 1, "year": 2016}, {"date": "2016-09-06", "lng": -74.00341, "lat": 40.708079999999995, "zipCode": 10038, "severityType": 0, "year": 2016}, {"date": "2016-09-02", "lng": -73.99805500000001, "lat": 40.711952000000004, "zipCode": 10038, "severityType": 0, "year": 2016}, {"date": "2016-09-02", "lng": -74.00418, "lat": 40.71024, "zipCode": 10038, "severityType": 0, "year": 2016}, {"date": "2016-08-31", "lng": -74.00775, "lat": 40.71022, "zipCode": 10038, "severityType": 0, "year": 2016}, {"date": "2016-08-30", "lng": -74.00501, "lat": 40.706852000000005, "zipCode": 10038, "severityType": 0, "year": 2016}, {"date": "2016-08-29", "lng": -74.00549000000001, "lat": 40.71135, "zipCode": 10038, "severityType": 0, "year": 2016}, {"date": "2016-08-29", "lng": -74.003265, "lat": 40.706184, "zipCode": 10038, "severityType": 0, "year": 2016}, {"date": "2016-08-26", "lng": -74.00426, "lat": 40.710163, "zipCode": 10038, "severityType": 0, "year": 2016}, {"date": "2016-08-25", "lng": -74.00729, "lat": 40.7087, "zipCode": 10038, "severityType": 0, "year": 2016}, {"date": "2016-08-24", "lng": -74.00107, "lat": 40.707417, "zipCode": 10038, "severityType": 1, "year": 2016}, {"date": "2016-08-24", "lng": -74.005775, "lat": 40.712086, "zipCode": 10038, "severityType": 0, "year": 2016}, {"date": "2016-08-23", "lng": -73.99971, "lat": 40.711777000000005, "zipCode": 10038, "severityType": 0, "year": 2016}, {"date": "2016-08-21", "lng": -74.00107, "lat": 40.707417, "zipCode": 10038, "severityType": 0, "year": 2016}, {"date": "2016-08-21", "lng": -74.006996, "lat": 40.711746000000005, "zipCode": 10038, "severityType": 0, "year": 2016}, {"date": "2016-08-20", "lng": -74.00166999999999, "lat": 40.709503000000005, "zipCode": 10038, "severityType": 0, "year": 2016}, {"date": "2016-08-20", "lng": -74.00107, "lat": 40.707417, "zipCode": 10038, "severityType": 0, "year": 2016}, {"date": "2016-08-19", "lng": -74.00029, "lat": 40.71119, "zipCode": 10038, "severityType": 0, "year": 2016}, {"date": "2016-08-17", "lng": -74.00522, "lat": 40.7067, "zipCode": 10038, "severityType": 0, "year": 2016}, {"date": "2016-08-17", "lng": -74.00166999999999, "lat": 40.709503000000005, "zipCode": 10038, "severityType": 0, "year": 2016}, {"date": "2016-08-17", "lng": -74.0009, "lat": 40.712357, "zipCode": 10038, "severityType": 0, "year": 2016}, {"date": "2016-08-16", "lng": -74.00166999999999, "lat": 40.709503000000005, "zipCode": 10038, "severityType": 0, "year": 2016}, {"date": "2016-08-16", "lng": -74.00775, "lat": 40.71022, "zipCode": 10038, "severityType": 0, "year": 2016}, {"date": "2016-08-16", "lng": -74.004196, "lat": 40.710205, "zipCode": 10038, "severityType": 0, "year": 2016}, {"date": "2016-08-13", "lng": -74.00525, "lat": 40.710045, "zipCode": 10038, "severityType": 0, "year": 2016}, {"date": "2016-08-12", "lng": -74.003876, "lat": 40.70579, "zipCode": 10038, "severityType": 0, "year": 2016}, {"date": "2016-08-10", "lng": -74.00963, "lat": 40.709644, "zipCode": 10038, "severityType": 1, "year": 2016}, {"date": "2016-08-10", "lng": -74.00166999999999, "lat": 40.709503000000005, "zipCode": 10038, "severityType": 0, "year": 2016}, {"date": "2016-08-09", "lng": -73.99868000000001, "lat": 40.711876000000004, "zipCode": 10038, "severityType": 0, "year": 2016}, {"date": "2016-08-06", "lng": -73.99889, "lat": 40.712596999999995, "zipCode": 10038, "severityType": 0, "year": 2016}, {"date": "2016-08-06", "lng": -73.99805500000001, "lat": 40.711952000000004, "zipCode": 10038, "severityType": 0, "year": 2016}, {"date": "2016-08-04", "lng": -74.00561, "lat": 40.710396, "zipCode": 10038, "severityType": 0, "year": 2016}, {"date": "2016-08-04", "lng": -74.00520999999999, "lat": 40.705994, "zipCode": 10038, "severityType": 0, "year": 2016}, {"date": "2016-08-03", "lng": -74.00341999999999, "lat": 40.7108, "zipCode": 10038, "severityType": 0, "year": 2016}, {"date": "2016-08-03", "lng": -74.00088000000001, "lat": 40.711696999999994, "zipCode": 10038, "severityType": 0, "year": 2016}, {"date": "2016-08-02", "lng": -74.00107, "lat": 40.707417, "zipCode": 10038, "severityType": 0, "year": 2016}, {"date": "2016-08-02", "lng": -74.00088000000001, "lat": 40.711696999999994, "zipCode": 10038, "severityType": 0, "year": 2016}, {"date": "2016-08-01", "lng": -74.007385, "lat": 40.71058, "zipCode": 10038, "severityType": 0, "year": 2016}, {"date": "2016-07-29", "lng": -74.00561, "lat": 40.710396, "zipCode": 10038, "severityType": 0, "year": 2016}, {"date": "2016-07-28", "lng": -74.00684, "lat": 40.707855, "zipCode": 10038, "severityType": 0, "year": 2016}, {"date": "2016-07-27", "lng": -74.0009, "lat": 40.712357, "zipCode": 10038, "severityType": 0, "year": 2016}, {"date": "2016-07-26", "lng": -74.00106, "lat": 40.7103, "zipCode": 10038, "severityType": 0, "year": 2016}, {"date": "2016-07-26", "lng": -74.00663, "lat": 40.7102, "zipCode": 10038, "severityType": 0, "year": 2016}, {"date": "2016-07-24", "lng": -74.005264, "lat": 40.70597, "zipCode": 10038, "severityType": 0, "year": 2016}, {"date": "2016-07-24", "lng": -74.00756, "lat": 40.708890000000004, "zipCode": 10038, "severityType": 0, "year": 2016}, {"date": "2016-07-23", "lng": -74.00684, "lat": 40.707855, "zipCode": 10038, "severityType": 0, "year": 2016}, {"date": "2016-07-22", "lng": -74.00775, "lat": 40.71022, "zipCode": 10038, "severityType": 0, "year": 2016}, {"date": "2016-07-20", "lng": -74.0057, "lat": 40.706375, "zipCode": 10038, "severityType": 0, "year": 2016}, {"date": "2016-07-20", "lng": -74.00166999999999, "lat": 40.709503000000005, "zipCode": 10038, "severityType": 0, "year": 2016}, {"date": "2016-07-16", "lng": -74.00549000000001, "lat": 40.707386, "zipCode": 10038, "severityType": 0, "year": 2016}, {"date": "2016-07-15", "lng": -74.00392, "lat": 40.710426, "zipCode": 10038, "severityType": 1, "year": 2016}, {"date": "2016-07-15", "lng": -74.00584, "lat": 40.711655, "zipCode": 10038, "severityType": 0, "year": 2016}, {"date": "2016-07-15", "lng": -74.0057, "lat": 40.706375, "zipCode": 10038, "severityType": 0, "year": 2016}, {"date": "2016-07-13", "lng": -73.99695600000001, "lat": 40.712070000000004, "zipCode": 10038, "severityType": 0, "year": 2016}, {"date": "2016-07-11", "lng": -74.0061, "lat": 40.711926, "zipCode": 10038, "severityType": 0, "year": 2016}, {"date": "2016-07-08", "lng": -73.997955, "lat": 40.712612, "zipCode": 10038, "severityType": 0, "year": 2016}, {"date": "2016-07-08", "lng": -74.00242, "lat": 40.70876, "zipCode": 10038, "severityType": 0, "year": 2016}, {"date": "2016-07-08", "lng": -74.00596, "lat": 40.707207000000004, "zipCode": 10038, "severityType": 0, "year": 2016}, {"date": "2016-07-07", "lng": -74.004265, "lat": 40.707336, "zipCode": 10038, "severityType": 0, "year": 2016}, {"date": "2016-07-07", "lng": -73.9992, "lat": 40.711838, "zipCode": 10038, "severityType": 0, "year": 2016}, {"date": "2016-07-06", "lng": -74.00275400000001, "lat": 40.707214, "zipCode": 10038, "severityType": 0, "year": 2016}, {"date": "2016-07-04", "lng": -74.00294, "lat": 40.708492, "zipCode": 10038, "severityType": 0, "year": 2016}, {"date": "2016-07-04", "lng": -74.00603000000001, "lat": 40.7079, "zipCode": 10038, "severityType": 0, "year": 2016}, {"date": "2016-07-04", "lng": -74.00166999999999, "lat": 40.709503000000005, "zipCode": 10038, "severityType": 0, "year": 2016}, {"date": "2016-07-03", "lng": -74.00635, "lat": 40.706394, "zipCode": 10038, "severityType": 0, "year": 2016}, {"date": "2016-07-03", "lng": -73.99889, "lat": 40.712596999999995, "zipCode": 10038, "severityType": 0, "year": 2016}, {"date": "2016-07-01", "lng": -74.00684, "lat": 40.707855, "zipCode": 10038, "severityType": 0, "year": 2016}, {"date": "2016-07-01", "lng": -74.00479, "lat": 40.7084, "zipCode": 10038, "severityType": 0, "year": 2016}, {"date": "2016-06-30", "lng": -74.00777, "lat": 40.707657, "zipCode": 10038, "severityType": 0, "year": 2016}, {"date": "2016-06-29", "lng": -74.00251, "lat": 40.708843, "zipCode": 10038, "severityType": 0, "year": 2016}, {"date": "2016-06-29", "lng": -74.00734, "lat": 40.707294, "zipCode": 10038, "severityType": 0, "year": 2016}, {"date": "2016-06-28", "lng": -74.00749, "lat": 40.71008, "zipCode": 10038, "severityType": 0, "year": 2016}, {"date": "2016-06-28", "lng": -74.00561, "lat": 40.710396, "zipCode": 10038, "severityType": 0, "year": 2016}, {"date": "2016-06-27", "lng": -74.00029, "lat": 40.71119, "zipCode": 10038, "severityType": 0, "year": 2016}, {"date": "2016-06-27", "lng": -74.00668, "lat": 40.710228, "zipCode": 10038, "severityType": 1, "year": 2016}, {"date": "2016-06-23", "lng": -74.00516, "lat": 40.709423, "zipCode": 10038, "severityType": 0, "year": 2016}, {"date": "2016-06-22", "lng": -74.00166999999999, "lat": 40.709503000000005, "zipCode": 10038, "severityType": 0, "year": 2016}, {"date": "2016-06-21", "lng": -74.0061, "lat": 40.711926, "zipCode": 10038, "severityType": 0, "year": 2016}, {"date": "2016-06-19", "lng": -74.00501, "lat": 40.706852000000005, "zipCode": 10038, "severityType": 0, "year": 2016}, {"date": "2016-06-19", "lng": -74.0009, "lat": 40.712357, "zipCode": 10038, "severityType": 0, "year": 2016}, {"date": "2016-06-19", "lng": -74.0061, "lat": 40.711926, "zipCode": 10038, "severityType": 0, "year": 2016}, {"date": "2016-06-16", "lng": -74.00549000000001, "lat": 40.707386, "zipCode": 10038, "severityType": 0, "year": 2016}, {"date": "2016-06-14", "lng": -73.99889, "lat": 40.712596999999995, "zipCode": 10038, "severityType": 0, "year": 2016}, {"date": "2016-06-14", "lng": -74.00251, "lat": 40.708843, "zipCode": 10038, "severityType": 0, "year": 2016}, {"date": "2016-06-14", "lng": -74.00294, "lat": 40.708492, "zipCode": 10038, "severityType": 0, "year": 2016}, {"date": "2016-06-09", "lng": -74.0009, "lat": 40.712357, "zipCode": 10038, "severityType": 0, "year": 2016}, {"date": "2016-06-08", "lng": -74.00501, "lat": 40.706852000000005, "zipCode": 10038, "severityType": 0, "year": 2016}, {"date": "2016-06-08", "lng": -73.99778, "lat": 40.71197, "zipCode": 10038, "severityType": 0, "year": 2016}, {"date": "2016-06-08", "lng": -74.00558000000001, "lat": 40.711407, "zipCode": 10038, "severityType": 0, "year": 2016}, {"date": "2016-06-07", "lng": -73.99679, "lat": 40.71136, "zipCode": 10038, "severityType": 0, "year": 2016}, {"date": "2016-06-06", "lng": -74.00341999999999, "lat": 40.7108, "zipCode": 10038, "severityType": 0, "year": 2016}, {"date": "2016-06-06", "lng": -74.00014, "lat": 40.707912, "zipCode": 10038, "severityType": 0, "year": 2016}, {"date": "2016-06-04", "lng": -73.99971, "lat": 40.711777000000005, "zipCode": 10038, "severityType": 0, "year": 2016}, {"date": "2016-06-03", "lng": -74.00166999999999, "lat": 40.709503000000005, "zipCode": 10038, "severityType": 0, "year": 2016}, {"date": "2016-06-03", "lng": -74.00310999999999, "lat": 40.70767, "zipCode": 10038, "severityType": 0, "year": 2016}, {"date": "2016-06-01", "lng": -74.00558000000001, "lat": 40.711407, "zipCode": 10038, "severityType": 0, "year": 2016}, {"date": "2016-05-31", "lng": -74.000786, "lat": 40.708675, "zipCode": 10038, "severityType": 0, "year": 2016}, {"date": "2016-05-31", "lng": -74.00014, "lat": 40.707912, "zipCode": 10038, "severityType": 0, "year": 2016}, {"date": "2016-05-29", "lng": -74.00644, "lat": 40.709557000000004, "zipCode": 10038, "severityType": 0, "year": 2016}, {"date": "2016-05-29", "lng": -73.99778, "lat": 40.71197, "zipCode": 10038, "severityType": 0, "year": 2016}, {"date": "2016-05-29", "lng": -73.99805500000001, "lat": 40.711952000000004, "zipCode": 10038, "severityType": 0, "year": 2016}, {"date": "2016-05-27", "lng": -74.00052, "lat": 40.710983, "zipCode": 10038, "severityType": 0, "year": 2016}, {"date": "2016-05-25", "lng": -74.00166999999999, "lat": 40.709503000000005, "zipCode": 10038, "severityType": 0, "year": 2016}, {"date": "2016-05-25", "lng": -74.00166999999999, "lat": 40.709503000000005, "zipCode": 10038, "severityType": 0, "year": 2016}, {"date": "2016-05-24", "lng": -74.00549000000001, "lat": 40.707386, "zipCode": 10038, "severityType": 0, "year": 2016}, {"date": "2016-05-23", "lng": -74.00086, "lat": 40.70879, "zipCode": 10038, "severityType": 0, "year": 2016}, {"date": "2016-05-22", "lng": -74.0061, "lat": 40.711926, "zipCode": 10038, "severityType": 0, "year": 2016}, {"date": "2016-05-21", "lng": -73.99889, "lat": 40.712596999999995, "zipCode": 10038, "severityType": 0, "year": 2016}, {"date": "2016-05-21", "lng": -73.99868000000001, "lat": 40.708755, "zipCode": 10038, "severityType": 0, "year": 2016}, {"date": "2016-05-20", "lng": -73.99889, "lat": 40.712596999999995, "zipCode": 10038, "severityType": 0, "year": 2016}, {"date": "2016-05-18", "lng": -74.00166999999999, "lat": 40.709503000000005, "zipCode": 10038, "severityType": 0, "year": 2016}, {"date": "2016-05-18", "lng": -74.003876, "lat": 40.70579, "zipCode": 10038, "severityType": 0, "year": 2016}, {"date": "2016-05-15", "lng": -74.00166999999999, "lat": 40.709503000000005, "zipCode": 10038, "severityType": 0, "year": 2016}, {"date": "2016-05-13", "lng": -74.00584, "lat": 40.711655, "zipCode": 10038, "severityType": 0, "year": 2016}, {"date": "2016-05-12", "lng": -73.99971, "lat": 40.711777000000005, "zipCode": 10038, "severityType": 0, "year": 2016}, {"date": "2016-05-10", "lng": -74.00501, "lat": 40.706852000000005, "zipCode": 10038, "severityType": 0, "year": 2016}, {"date": "2016-05-10", "lng": -74.007385, "lat": 40.71058, "zipCode": 10038, "severityType": 0, "year": 2016}, {"date": "2016-05-09", "lng": -74.001144, "lat": 40.710175, "zipCode": 10038, "severityType": 0, "year": 2016}, {"date": "2016-05-09", "lng": -74.0061, "lat": 40.711926, "zipCode": 10038, "severityType": 0, "year": 2016}, {"date": "2016-05-07", "lng": -74.00654, "lat": 40.708225, "zipCode": 10038, "severityType": 0, "year": 2016}, {"date": "2016-05-06", "lng": -74.006996, "lat": 40.711746000000005, "zipCode": 10038, "severityType": 0, "year": 2016}, {"date": "2016-05-04", "lng": -73.99665999999999, "lat": 40.710876, "zipCode": 10038, "severityType": 0, "year": 2016}, {"date": "2016-04-29", "lng": -74.00842, "lat": 40.70953, "zipCode": 10038, "severityType": 0, "year": 2016}, {"date": "2016-04-27", "lng": -74.005516, "lat": 40.710471999999996, "zipCode": 10038, "severityType": 0, "year": 2016}, {"date": "2016-04-23", "lng": -74.00623, "lat": 40.707397, "zipCode": 10038, "severityType": 0, "year": 2016}, {"date": "2016-04-16", "lng": -74.004265, "lat": 40.707336, "zipCode": 10038, "severityType": 0, "year": 2016}, {"date": "2016-04-15", "lng": -74.00647, "lat": 40.70817, "zipCode": 10038, "severityType": 0, "year": 2016}, {"date": "2016-04-14", "lng": -74.00426, "lat": 40.710163, "zipCode": 10038, "severityType": 0, "year": 2016}, {"date": "2016-04-06", "lng": -74.00654, "lat": 40.708225, "zipCode": 10038, "severityType": 0, "year": 2016}, {"date": "2016-04-05", "lng": -74.00085, "lat": 40.71055, "zipCode": 10038, "severityType": 0, "year": 2016}, {"date": "2016-04-04", "lng": -74.00516, "lat": 40.709423, "zipCode": 10038, "severityType": 0, "year": 2016}, {"date": "2016-04-01", "lng": -74.00310999999999, "lat": 40.70767, "zipCode": 10038, "severityType": 0, "year": 2016}, {"date": "2016-03-31", "lng": -73.99633, "lat": 40.70991, "zipCode": 10038, "severityType": 0, "year": 2016}, {"date": "2016-03-19", "lng": -73.99763, "lat": 40.713440000000006, "zipCode": 10038, "severityType": 0, "year": 2016}, {"date": "2016-03-18", "lng": -74.0009, "lat": 40.712357, "zipCode": 10038, "severityType": 0, "year": 2016}, {"date": "2016-03-13", "lng": -74.0011362, "lat": 40.710176700000005, "zipCode": 10038, "severityType": 0, "year": 2016}, {"date": "2016-03-11", "lng": -74.00559809999999, "lat": 40.710396100000004, "zipCode": 10038, "severityType": 0, "year": 2016}, {"date": "2016-03-11", "lng": -74.0025032, "lat": 40.708845399999994, "zipCode": 10038, "severityType": 0, "year": 2016}, {"date": "2016-03-10", "lng": -74.0011362, "lat": 40.710176700000005, "zipCode": 10038, "severityType": 0, "year": 2016}, {"date": "2016-03-09", "lng": -74.00482609999999, "lat": 40.7096605, "zipCode": 10038, "severityType": 0, "year": 2016}, {"date": "2016-03-08", "lng": -74.00387009999999, "lat": 40.7057932, "zipCode": 10038, "severityType": 0, "year": 2016}, {"date": "2016-03-07", "lng": -74.00514709999999, "lat": 40.7094245, "zipCode": 10038, "severityType": 0, "year": 2016}, {"date": "2016-03-07", "lng": -74.0014824, "lat": 40.7078573, "zipCode": 10038, "severityType": 0, "year": 2016}, {"date": "2016-03-06", "lng": -74.00841870000001, "lat": 40.709531299999995, "zipCode": 10038, "severityType": 0, "year": 2016}, {"date": "2016-03-05", "lng": -74.0069869, "lat": 40.711738200000006, "zipCode": 10038, "severityType": 1, "year": 2016}, {"date": "2016-03-02", "lng": -74.00595129999999, "lat": 40.7072067, "zipCode": 10038, "severityType": 0, "year": 2016}, {"date": "2016-03-01", "lng": -74.00050859999999, "lat": 40.7109836, "zipCode": 10038, "severityType": 0, "year": 2016}, {"date": "2016-02-28", "lng": -73.9982253, "lat": 40.7132425, "zipCode": 10038, "severityType": 0, "year": 2016}, {"date": "2016-02-25", "lng": -73.99798359999998, "lat": 40.7127265, "zipCode": 10038, "severityType": 0, "year": 2016}, {"date": "2016-02-24", "lng": -74.0056915, "lat": 40.706375, "zipCode": 10038, "severityType": 0, "year": 2016}, {"date": "2016-02-23", "lng": -74.0016664, "lat": 40.7095234, "zipCode": 10038, "severityType": 0, "year": 2016}, {"date": "2016-02-21", "lng": -74.0060886, "lat": 40.709913, "zipCode": 10038, "severityType": 0, "year": 2016}, {"date": "2016-02-21", "lng": -74.00246, "lat": 40.711571, "zipCode": 10038, "severityType": 0, "year": 2016}, {"date": "2016-02-18", "lng": -74.0011362, "lat": 40.710176700000005, "zipCode": 10038, "severityType": 0, "year": 2016}, {"date": "2016-02-18", "lng": -74.0050027, "lat": 40.7068526, "zipCode": 10038, "severityType": 0, "year": 2016}, {"date": "2016-02-18", "lng": -74.0064783, "lat": 40.7112305, "zipCode": 10038, "severityType": 0, "year": 2016}, {"date": "2016-02-16", "lng": -74.00190079999999, "lat": 40.7082718, "zipCode": 10038, "severityType": 0, "year": 2016}, {"date": "2016-02-16", "lng": -74.005936, "lat": 40.710087, "zipCode": 10038, "severityType": 0, "year": 2016}, {"date": "2016-02-13", "lng": -74.0011362, "lat": 40.710176700000005, "zipCode": 10038, "severityType": 0, "year": 2016}, {"date": "2016-02-08", "lng": -74.0016664, "lat": 40.7095234, "zipCode": 10038, "severityType": 0, "year": 2016}, {"date": "2016-02-07", "lng": -74.0025032, "lat": 40.708845399999994, "zipCode": 10038, "severityType": 1, "year": 2016}, {"date": "2016-02-07", "lng": -74.0065321, "lat": 40.7082277, "zipCode": 10038, "severityType": 0, "year": 2016}, {"date": "2016-02-07", "lng": -74.0016664, "lat": 40.7095234, "zipCode": 10038, "severityType": 0, "year": 2016}, {"date": "2016-02-07", "lng": -74.00431379999999, "lat": 40.70726989999999, "zipCode": 10038, "severityType": 0, "year": 2016}, {"date": "2016-02-06", "lng": -73.9997006, "lat": 40.7117796, "zipCode": 10038, "severityType": 1, "year": 2016}, {"date": "2016-02-05", "lng": -74.0016664, "lat": 40.7095234, "zipCode": 10038, "severityType": 0, "year": 2016}, {"date": "2016-02-04", "lng": -74.007286, "lat": 40.708699700000004, "zipCode": 10038, "severityType": 0, "year": 2016}, {"date": "2016-02-02", "lng": -74.0060886, "lat": 40.709913, "zipCode": 10038, "severityType": 0, "year": 2016}, {"date": "2016-02-02", "lng": -74.0068386, "lat": 40.7078571, "zipCode": 10038, "severityType": 0, "year": 2016}, {"date": "2016-02-01", "lng": -74.0008729, "lat": 40.7116973, "zipCode": 10038, "severityType": 0, "year": 2016}, {"date": "2016-01-29", "lng": -74.0011362, "lat": 40.710176700000005, "zipCode": 10038, "severityType": 0, "year": 2016}, {"date": "2016-01-29", "lng": -74.00573890000001, "lat": 40.7120896, "zipCode": 10038, "severityType": 0, "year": 2016}, {"date": "2016-01-29", "lng": -74.0076394, "lat": 40.7083456, "zipCode": 10038, "severityType": 0, "year": 2016}, {"date": "2016-01-28", "lng": -74.0008584, "lat": 40.708790500000006, "zipCode": 10038, "severityType": 0, "year": 2016}, {"date": "2016-01-28", "lng": -74.0064562, "lat": 40.7069816, "zipCode": 10038, "severityType": 0, "year": 2016}, {"date": "2016-01-27", "lng": -74.00233, "lat": 40.7067073, "zipCode": 10038, "severityType": 0, "year": 2016}, {"date": "2016-01-26", "lng": -74.0042527, "lat": 40.7101656, "zipCode": 10038, "severityType": 1, "year": 2016}, {"date": "2016-01-26", "lng": -74.007286, "lat": 40.708699700000004, "zipCode": 10038, "severityType": 0, "year": 2016}, {"date": "2016-01-26", "lng": -74.00559809999999, "lat": 40.710396100000004, "zipCode": 10038, "severityType": 0, "year": 2016}, {"date": "2016-01-25", "lng": -73.9982253, "lat": 40.7132425, "zipCode": 10038, "severityType": 0, "year": 2016}, {"date": "2016-01-25", "lng": -74.0064783, "lat": 40.7112305, "zipCode": 10038, "severityType": 0, "year": 2016}, {"date": "2016-01-22", "lng": -74.0008729, "lat": 40.7116973, "zipCode": 10038, "severityType": 0, "year": 2016}, {"date": "2016-01-22", "lng": -74.00310909999999, "lat": 40.7076706, "zipCode": 10038, "severityType": 0, "year": 2016}, {"date": "2016-01-21", "lng": -74.0068386, "lat": 40.7078571, "zipCode": 10038, "severityType": 0, "year": 2016}, {"date": "2016-01-20", "lng": -74.00050859999999, "lat": 40.7109836, "zipCode": 10038, "severityType": 0, "year": 2016}, {"date": "2016-01-19", "lng": -74.0001298, "lat": 40.7079122, "zipCode": 10038, "severityType": 0, "year": 2016}, {"date": "2016-01-16", "lng": -74.00337979999999, "lat": 40.7108271, "zipCode": 10038, "severityType": 1, "year": 2016}, {"date": "2016-01-16", "lng": -74.00737640000001, "lat": 40.7105799, "zipCode": 10038, "severityType": 0, "year": 2016}, {"date": "2016-01-16", "lng": -74.0064783, "lat": 40.7112305, "zipCode": 10038, "severityType": 0, "year": 2016}, {"date": "2016-01-14", "lng": -74.00337979999999, "lat": 40.7108271, "zipCode": 10038, "severityType": 0, "year": 2016}, {"date": "2016-01-13", "lng": -74.005829, "lat": 40.711655900000004, "zipCode": 10038, "severityType": 0, "year": 2016}, {"date": "2016-01-13", "lng": -74.00482609999999, "lat": 40.7096605, "zipCode": 10038, "severityType": 0, "year": 2016}, {"date": "2016-01-13", "lng": -74.00089100000001, "lat": 40.712356, "zipCode": 10038, "severityType": 0, "year": 2016}, {"date": "2016-01-12", "lng": -74.0077442, "lat": 40.710220299999996, "zipCode": 10038, "severityType": 0, "year": 2016}, {"date": "2016-01-12", "lng": -73.99694840000001, "lat": 40.7120705, "zipCode": 10038, "severityType": 0, "year": 2016}, {"date": "2016-01-11", "lng": -74.0042527, "lat": 40.7101656, "zipCode": 10038, "severityType": 1, "year": 2016}, {"date": "2016-01-10", "lng": -74.0011362, "lat": 40.710176700000005, "zipCode": 10038, "severityType": 0, "year": 2016}, {"date": "2016-01-07", "lng": -74.0055114, "lat": 40.709092299999995, "zipCode": 10038, "severityType": 0, "year": 2016}, {"date": "2016-01-06", "lng": -74.0034013, "lat": 40.708082399999995, "zipCode": 10038, "severityType": 0, "year": 2016}, {"date": "2016-01-06", "lng": -74.0048152, "lat": 40.708389700000005, "zipCode": 10038, "severityType": 0, "year": 2016}, {"date": "2016-01-06", "lng": -74.0048152, "lat": 40.708389700000005, "zipCode": 10038, "severityType": 0, "year": 2016}, {"date": "2016-01-06", "lng": -73.99798359999998, "lat": 40.7127265, "zipCode": 10038, "severityType": 0, "year": 2016}, {"date": "2016-01-03", "lng": -74.0048152, "lat": 40.708389700000005, "zipCode": 10038, "severityType": 0, "year": 2016}]