[{"date": "2015-12-31", "lng": -73.7928495, "lat": 40.7044239, "zipCode": 11433, "severityType": 0, "year": 2015}, {"date": "2015-12-31", "lng": -73.7825671, "lat": 40.705426, "zipCode": 11433, "severityType": 0, "year": 2015}, {"date": "2015-12-30", "lng": -73.79712409999999, "lat": 40.7030344, "zipCode": 11433, "severityType": 0, "year": 2015}, {"date": "2015-12-30", "lng": -73.79521319999999, "lat": 40.696962299999996, "zipCode": 11433, "severityType": 0, "year": 2015}, {"date": "2015-12-29", "lng": -73.7802385, "lat": 40.6929712, "zipCode": 11433, "severityType": 0, "year": 2015}, {"date": "2015-12-29", "lng": -73.7802385, "lat": 40.6929712, "zipCode": 11433, "severityType": 0, "year": 2015}, {"date": "2015-12-29", "lng": -73.7983005, "lat": 40.6956558, "zipCode": 11433, "severityType": 0, "year": 2015}, {"date": "2015-12-26", "lng": -73.7873116, "lat": 40.70154, "zipCode": 11433, "severityType": 0, "year": 2015}, {"date": "2015-12-24", "lng": -73.79008759999999, "lat": 40.6949823, "zipCode": 11433, "severityType": 1, "year": 2015}, {"date": "2015-12-22", "lng": -73.79165429999999, "lat": 40.7048554, "zipCode": 11433, "severityType": 0, "year": 2015}, {"date": "2015-12-21", "lng": -73.7802385, "lat": 40.6929712, "zipCode": 11433, "severityType": 0, "year": 2015}, {"date": "2015-12-20", "lng": -73.7891055, "lat": 40.695386799999994, "zipCode": 11433, "severityType": 0, "year": 2015}, {"date": "2015-12-19", "lng": -73.79677109999999, "lat": 40.7005141, "zipCode": 11433, "severityType": 1, "year": 2015}, {"date": "2015-12-19", "lng": -73.77874759999999, "lat": 40.6956336, "zipCode": 11433, "severityType": 0, "year": 2015}, {"date": "2015-12-17", "lng": -73.8024077, "lat": 40.7018524, "zipCode": 11433, "severityType": 0, "year": 2015}, {"date": "2015-12-17", "lng": -73.7921314, "lat": 40.694115999999994, "zipCode": 11433, "severityType": 0, "year": 2015}, {"date": "2015-12-17", "lng": -73.7978607, "lat": 40.6979935, "zipCode": 11433, "severityType": 0, "year": 2015}, {"date": "2015-12-16", "lng": -73.78516440000001, "lat": 40.7064025, "zipCode": 11433, "severityType": 0, "year": 2015}, {"date": "2015-12-16", "lng": -73.78146329999998, "lat": 40.694469500000004, "zipCode": 11433, "severityType": 0, "year": 2015}, {"date": "2015-12-16", "lng": -73.78146329999998, "lat": 40.694469500000004, "zipCode": 11433, "severityType": 0, "year": 2015}, {"date": "2015-12-16", "lng": -73.7928495, "lat": 40.7044239, "zipCode": 11433, "severityType": 0, "year": 2015}, {"date": "2015-12-15", "lng": -73.7793745, "lat": 40.7078133, "zipCode": 11433, "severityType": 0, "year": 2015}, {"date": "2015-12-15", "lng": -73.7963245, "lat": 40.6944171, "zipCode": 11433, "severityType": 0, "year": 2015}, {"date": "2015-12-13", "lng": -73.7849603, "lat": 40.7003636, "zipCode": 11433, "severityType": 0, "year": 2015}, {"date": "2015-12-13", "lng": -73.79677109999999, "lat": 40.7005141, "zipCode": 11433, "severityType": 1, "year": 2015}, {"date": "2015-12-12", "lng": -73.78146329999998, "lat": 40.694469500000004, "zipCode": 11433, "severityType": 0, "year": 2015}, {"date": "2015-12-11", "lng": -73.7802385, "lat": 40.6929712, "zipCode": 11433, "severityType": 0, "year": 2015}, {"date": "2015-12-10", "lng": -73.7959842, "lat": 40.6924815, "zipCode": 11433, "severityType": 0, "year": 2015}, {"date": "2015-12-09", "lng": -73.78884980000001, "lat": 40.7055035, "zipCode": 11433, "severityType": 0, "year": 2015}, {"date": "2015-12-09", "lng": -73.7825671, "lat": 40.705426, "zipCode": 11433, "severityType": 1, "year": 2015}, {"date": "2015-12-08", "lng": -73.7920324, "lat": 40.6900123, "zipCode": 11433, "severityType": 0, "year": 2015}, {"date": "2015-12-08", "lng": -73.7960918, "lat": 40.7032933, "zipCode": 11433, "severityType": 0, "year": 2015}, {"date": "2015-12-07", "lng": -73.8024077, "lat": 40.7018524, "zipCode": 11433, "severityType": 1, "year": 2015}, {"date": "2015-12-06", "lng": -73.78337049999999, "lat": 40.7068328, "zipCode": 11433, "severityType": 0, "year": 2015}, {"date": "2015-12-05", "lng": -73.7928495, "lat": 40.7044239, "zipCode": 11433, "severityType": 0, "year": 2015}, {"date": "2015-12-05", "lng": -73.7834279, "lat": 40.694701, "zipCode": 11433, "severityType": 1, "year": 2015}, {"date": "2015-12-05", "lng": -73.7848493, "lat": 40.7045849, "zipCode": 11433, "severityType": 1, "year": 2015}, {"date": "2015-12-04", "lng": -73.78778249999999, "lat": 40.6918189, "zipCode": 11433, "severityType": 0, "year": 2015}, {"date": "2015-12-04", "lng": -73.7808694, "lat": 40.7029113, "zipCode": 11433, "severityType": 0, "year": 2015}, {"date": "2015-12-04", "lng": -73.799184, "lat": 40.6968705, "zipCode": 11433, "severityType": 0, "year": 2015}, {"date": "2015-12-03", "lng": -73.79712409999999, "lat": 40.7030344, "zipCode": 11433, "severityType": 0, "year": 2015}, {"date": "2015-12-03", "lng": -73.7999209, "lat": 40.7024739, "zipCode": 11433, "severityType": 0, "year": 2015}, {"date": "2015-12-03", "lng": -73.7960918, "lat": 40.7032933, "zipCode": 11433, "severityType": 0, "year": 2015}, {"date": "2015-12-02", "lng": -73.7878205, "lat": 40.6980112, "zipCode": 11433, "severityType": 0, "year": 2015}, {"date": "2015-12-02", "lng": -73.7986849, "lat": 40.699715999999995, "zipCode": 11433, "severityType": 0, "year": 2015}, {"date": "2015-12-01", "lng": -73.7966612, "lat": 40.6963501, "zipCode": 11433, "severityType": 0, "year": 2015}, {"date": "2015-12-01", "lng": -73.79677109999999, "lat": 40.7005141, "zipCode": 11433, "severityType": 1, "year": 2015}, {"date": "2015-11-30", "lng": -73.79545590000001, "lat": 40.6895519, "zipCode": 11433, "severityType": 0, "year": 2015}, {"date": "2015-11-30", "lng": -73.79172270000001, "lat": 40.6921994, "zipCode": 11433, "severityType": 0, "year": 2015}, {"date": "2015-11-30", "lng": -73.8018952, "lat": 40.701969500000004, "zipCode": 11433, "severityType": 1, "year": 2015}, {"date": "2015-11-29", "lng": -73.7825671, "lat": 40.705426, "zipCode": 11433, "severityType": 0, "year": 2015}, {"date": "2015-11-29", "lng": -73.7984161, "lat": 40.7027402, "zipCode": 11433, "severityType": 0, "year": 2015}, {"date": "2015-11-29", "lng": -73.78087059999999, "lat": 40.692662299999995, "zipCode": 11433, "severityType": 0, "year": 2015}, {"date": "2015-11-28", "lng": -73.79165429999999, "lat": 40.7048554, "zipCode": 11433, "severityType": 1, "year": 2015}, {"date": "2015-11-28", "lng": -73.7848493, "lat": 40.7045849, "zipCode": 11433, "severityType": 0, "year": 2015}, {"date": "2015-11-28", "lng": -73.79239129999999, "lat": 40.70216679999999, "zipCode": 11433, "severityType": 0, "year": 2015}, {"date": "2015-11-27", "lng": -73.794641, "lat": 40.70123770000001, "zipCode": 11433, "severityType": 0, "year": 2015}, {"date": "2015-11-27", "lng": -73.7928495, "lat": 40.7044239, "zipCode": 11433, "severityType": 0, "year": 2015}, {"date": "2015-11-25", "lng": -73.7844195, "lat": 40.7047625, "zipCode": 11433, "severityType": 0, "year": 2015}, {"date": "2015-11-25", "lng": -73.79026529999999, "lat": 40.7015564, "zipCode": 11433, "severityType": 0, "year": 2015}, {"date": "2015-11-25", "lng": -73.78529820000001, "lat": 40.6928573, "zipCode": 11433, "severityType": 0, "year": 2015}, {"date": "2015-11-24", "lng": -73.78146329999998, "lat": 40.694469500000004, "zipCode": 11433, "severityType": 0, "year": 2015}, {"date": "2015-11-24", "lng": -73.7802385, "lat": 40.6929712, "zipCode": 11433, "severityType": 0, "year": 2015}, {"date": "2015-11-24", "lng": -73.79379200000001, "lat": 40.704033100000004, "zipCode": 11433, "severityType": 0, "year": 2015}, {"date": "2015-11-24", "lng": -73.79008759999999, "lat": 40.6949823, "zipCode": 11433, "severityType": 1, "year": 2015}, {"date": "2015-11-23", "lng": -73.79677109999999, "lat": 40.7005141, "zipCode": 11433, "severityType": 0, "year": 2015}, {"date": "2015-11-23", "lng": -73.794641, "lat": 40.70123770000001, "zipCode": 11433, "severityType": 0, "year": 2015}, {"date": "2015-11-23", "lng": -73.799184, "lat": 40.6968705, "zipCode": 11433, "severityType": 0, "year": 2015}, {"date": "2015-11-22", "lng": -73.79008759999999, "lat": 40.6949823, "zipCode": 11433, "severityType": 0, "year": 2015}, {"date": "2015-11-22", "lng": -73.7960918, "lat": 40.7032933, "zipCode": 11433, "severityType": 0, "year": 2015}, {"date": "2015-11-22", "lng": -73.7802385, "lat": 40.6929712, "zipCode": 11433, "severityType": 0, "year": 2015}, {"date": "2015-11-22", "lng": -73.7870573, "lat": 40.6908294, "zipCode": 11433, "severityType": 0, "year": 2015}, {"date": "2015-11-21", "lng": -73.78210990000001, "lat": 40.6952365, "zipCode": 11433, "severityType": 0, "year": 2015}, {"date": "2015-11-21", "lng": -73.7909536, "lat": 40.6925273, "zipCode": 11433, "severityType": 0, "year": 2015}, {"date": "2015-11-21", "lng": -73.77946740000002, "lat": 40.700435600000006, "zipCode": 11433, "severityType": 0, "year": 2015}, {"date": "2015-11-21", "lng": -73.7717522, "lat": 40.6975303, "zipCode": 11433, "severityType": 0, "year": 2015}, {"date": "2015-11-20", "lng": -73.79379200000001, "lat": 40.704033100000004, "zipCode": 11433, "severityType": 0, "year": 2015}, {"date": "2015-11-20", "lng": -73.79240379999999, "lat": 40.6981513, "zipCode": 11433, "severityType": 0, "year": 2015}, {"date": "2015-11-20", "lng": -73.7908645, "lat": 40.7036765, "zipCode": 11433, "severityType": 0, "year": 2015}, {"date": "2015-11-20", "lng": -73.7984161, "lat": 40.7027402, "zipCode": 11433, "severityType": 0, "year": 2015}, {"date": "2015-11-19", "lng": -73.78269559999998, "lat": 40.6981059, "zipCode": 11433, "severityType": 0, "year": 2015}, {"date": "2015-11-19", "lng": -73.7844195, "lat": 40.7047625, "zipCode": 11433, "severityType": 0, "year": 2015}, {"date": "2015-11-19", "lng": -73.80210109999999, "lat": 40.7006414, "zipCode": 11433, "severityType": 0, "year": 2015}, {"date": "2015-11-18", "lng": -73.7844195, "lat": 40.7047625, "zipCode": 11433, "severityType": 0, "year": 2015}, {"date": "2015-11-17", "lng": -73.7793745, "lat": 40.7078133, "zipCode": 11433, "severityType": 0, "year": 2015}, {"date": "2015-11-17", "lng": -73.79165429999999, "lat": 40.7048554, "zipCode": 11433, "severityType": 1, "year": 2015}, {"date": "2015-11-17", "lng": -73.7895391, "lat": 40.7008222, "zipCode": 11433, "severityType": 0, "year": 2015}, {"date": "2015-11-17", "lng": -73.7825671, "lat": 40.705426, "zipCode": 11433, "severityType": 0, "year": 2015}, {"date": "2015-11-16", "lng": -73.79318149999999, "lat": 40.691584399999996, "zipCode": 11433, "severityType": 0, "year": 2015}, {"date": "2015-11-16", "lng": -73.7999209, "lat": 40.7024739, "zipCode": 11433, "severityType": 0, "year": 2015}, {"date": "2015-11-15", "lng": -73.7891925, "lat": 40.703204, "zipCode": 11433, "severityType": 0, "year": 2015}, {"date": "2015-11-14", "lng": -73.77730559999999, "lat": 40.6922547, "zipCode": 11433, "severityType": 0, "year": 2015}, {"date": "2015-11-14", "lng": -73.7839338, "lat": 40.6954952, "zipCode": 11433, "severityType": 0, "year": 2015}, {"date": "2015-11-13", "lng": -73.7984161, "lat": 40.7027402, "zipCode": 11433, "severityType": 0, "year": 2015}, {"date": "2015-11-13", "lng": -73.7878205, "lat": 40.6980112, "zipCode": 11433, "severityType": 0, "year": 2015}, {"date": "2015-11-12", "lng": -73.7913825, "lat": 40.6902856, "zipCode": 11433, "severityType": 0, "year": 2015}, {"date": "2015-11-12", "lng": -73.7808694, "lat": 40.7029113, "zipCode": 11433, "severityType": 0, "year": 2015}, {"date": "2015-11-12", "lng": -73.7960918, "lat": 40.7032933, "zipCode": 11433, "severityType": 0, "year": 2015}, {"date": "2015-11-10", "lng": -73.79449890000001, "lat": 40.6993847, "zipCode": 11433, "severityType": 1, "year": 2015}, {"date": "2015-11-10", "lng": -73.7903739, "lat": 40.699124700000006, "zipCode": 11433, "severityType": 1, "year": 2015}, {"date": "2015-11-10", "lng": -73.79357809999999, "lat": 40.6997563, "zipCode": 11433, "severityType": 0, "year": 2015}, {"date": "2015-11-09", "lng": -73.7895391, "lat": 40.7008222, "zipCode": 11433, "severityType": 0, "year": 2015}, {"date": "2015-11-09", "lng": -73.79677109999999, "lat": 40.7005141, "zipCode": 11433, "severityType": 1, "year": 2015}, {"date": "2015-11-09", "lng": -73.7739552, "lat": 40.6998045, "zipCode": 11433, "severityType": 0, "year": 2015}, {"date": "2015-11-07", "lng": -73.7881564, "lat": 40.7012671, "zipCode": 11433, "severityType": 0, "year": 2015}, {"date": "2015-11-07", "lng": -73.7825671, "lat": 40.705426, "zipCode": 11433, "severityType": 0, "year": 2015}, {"date": "2015-11-06", "lng": -73.7831407, "lat": 40.7020702, "zipCode": 11433, "severityType": 0, "year": 2015}, {"date": "2015-11-05", "lng": -73.8010546, "lat": 40.6984191, "zipCode": 11433, "severityType": 0, "year": 2015}, {"date": "2015-11-05", "lng": -73.7928444, "lat": 40.7002436, "zipCode": 11433, "severityType": 0, "year": 2015}, {"date": "2015-11-05", "lng": -73.79042779999999, "lat": 40.6969125, "zipCode": 11433, "severityType": 1, "year": 2015}, {"date": "2015-11-03", "lng": -73.78642190000001, "lat": 40.6978027, "zipCode": 11433, "severityType": 0, "year": 2015}, {"date": "2015-11-03", "lng": -73.77792149999999, "lat": 40.703292600000005, "zipCode": 11433, "severityType": 0, "year": 2015}, {"date": "2015-11-02", "lng": -73.7834279, "lat": 40.694701, "zipCode": 11433, "severityType": 0, "year": 2015}, {"date": "2015-11-01", "lng": -73.79550479999999, "lat": 40.694764299999996, "zipCode": 11433, "severityType": 0, "year": 2015}, {"date": "2015-10-30", "lng": -73.7984161, "lat": 40.7027402, "zipCode": 11433, "severityType": 0, "year": 2015}, {"date": "2015-10-30", "lng": -73.783825, "lat": 40.7079288, "zipCode": 11433, "severityType": 0, "year": 2015}, {"date": "2015-10-30", "lng": -73.7881046, "lat": 40.6937326, "zipCode": 11433, "severityType": 1, "year": 2015}, {"date": "2015-10-29", "lng": -73.7895391, "lat": 40.7008222, "zipCode": 11433, "severityType": 0, "year": 2015}, {"date": "2015-10-28", "lng": -73.789845, "lat": 40.6930057, "zipCode": 11433, "severityType": 0, "year": 2015}, {"date": "2015-10-28", "lng": -73.78284520000001, "lat": 40.69976679999999, "zipCode": 11433, "severityType": 0, "year": 2015}, {"date": "2015-10-28", "lng": -73.78153950000001, "lat": 40.6965227, "zipCode": 11433, "severityType": 0, "year": 2015}, {"date": "2015-10-28", "lng": -73.78284520000001, "lat": 40.69976679999999, "zipCode": 11433, "severityType": 0, "year": 2015}, {"date": "2015-10-28", "lng": -73.7831407, "lat": 40.7020702, "zipCode": 11433, "severityType": 0, "year": 2015}, {"date": "2015-10-27", "lng": -73.77748340000001, "lat": 40.6930016, "zipCode": 11433, "severityType": 0, "year": 2015}, {"date": "2015-10-27", "lng": -73.79732920000001, "lat": 40.6972488, "zipCode": 11433, "severityType": 0, "year": 2015}, {"date": "2015-10-27", "lng": -73.7933174, "lat": 40.6977604, "zipCode": 11433, "severityType": 0, "year": 2015}, {"date": "2015-10-27", "lng": -73.79026529999999, "lat": 40.7015564, "zipCode": 11433, "severityType": 0, "year": 2015}, {"date": "2015-10-27", "lng": -73.7825671, "lat": 40.705426, "zipCode": 11433, "severityType": 0, "year": 2015}, {"date": "2015-10-26", "lng": -73.8024077, "lat": 40.7018524, "zipCode": 11433, "severityType": 0, "year": 2015}, {"date": "2015-10-26", "lng": -73.7998599, "lat": 40.6963474, "zipCode": 11433, "severityType": 0, "year": 2015}, {"date": "2015-10-26", "lng": -73.79042779999999, "lat": 40.6969125, "zipCode": 11433, "severityType": 0, "year": 2015}, {"date": "2015-10-26", "lng": -73.79379200000001, "lat": 40.704033100000004, "zipCode": 11433, "severityType": 2, "year": 2015}, {"date": "2015-10-24", "lng": -73.7909536, "lat": 40.6925273, "zipCode": 11433, "severityType": 0, "year": 2015}, {"date": "2015-10-23", "lng": -73.79329129999999, "lat": 40.695701799999995, "zipCode": 11433, "severityType": 0, "year": 2015}, {"date": "2015-10-23", "lng": -73.78210990000001, "lat": 40.6952365, "zipCode": 11433, "severityType": 0, "year": 2015}, {"date": "2015-10-23", "lng": -73.790862, "lat": 40.688407299999994, "zipCode": 11433, "severityType": 0, "year": 2015}, {"date": "2015-10-23", "lng": -73.782771, "lat": 40.6959953, "zipCode": 11433, "severityType": 0, "year": 2015}, {"date": "2015-10-23", "lng": -73.79677109999999, "lat": 40.7005141, "zipCode": 11433, "severityType": 1, "year": 2015}, {"date": "2015-10-22", "lng": -73.7972118, "lat": 40.691962100000005, "zipCode": 11433, "severityType": 0, "year": 2015}, {"date": "2015-10-22", "lng": -73.7892715, "lat": 40.6953267, "zipCode": 11433, "severityType": 0, "year": 2015}, {"date": "2015-10-22", "lng": -73.791937, "lat": 40.703253000000004, "zipCode": 11433, "severityType": 0, "year": 2015}, {"date": "2015-10-21", "lng": -73.7928495, "lat": 40.7044239, "zipCode": 11433, "severityType": 1, "year": 2015}, {"date": "2015-10-21", "lng": -73.7928495, "lat": 40.7044239, "zipCode": 11433, "severityType": 0, "year": 2015}, {"date": "2015-10-21", "lng": -73.7967665, "lat": 40.69135479999999, "zipCode": 11433, "severityType": 0, "year": 2015}, {"date": "2015-10-20", "lng": -73.79357809999999, "lat": 40.6997563, "zipCode": 11433, "severityType": 0, "year": 2015}, {"date": "2015-10-17", "lng": -73.7865546, "lat": 40.69014779999999, "zipCode": 11433, "severityType": 0, "year": 2015}, {"date": "2015-10-16", "lng": -73.78609509999998, "lat": 40.689501899999996, "zipCode": 11433, "severityType": 0, "year": 2015}, {"date": "2015-10-15", "lng": -73.79239129999999, "lat": 40.70216679999999, "zipCode": 11433, "severityType": 0, "year": 2015}, {"date": "2015-10-14", "lng": -73.78893149999999, "lat": 40.693396500000006, "zipCode": 11433, "severityType": 1, "year": 2015}, {"date": "2015-10-14", "lng": -73.7831993, "lat": 40.7006979, "zipCode": 11433, "severityType": 0, "year": 2015}, {"date": "2015-10-14", "lng": -73.7999209, "lat": 40.7024739, "zipCode": 11433, "severityType": 0, "year": 2015}, {"date": "2015-10-13", "lng": -73.782771, "lat": 40.6959953, "zipCode": 11433, "severityType": 0, "year": 2015}, {"date": "2015-10-12", "lng": -73.79026529999999, "lat": 40.7015564, "zipCode": 11433, "severityType": 0, "year": 2015}, {"date": "2015-10-12", "lng": -73.7999209, "lat": 40.7024739, "zipCode": 11433, "severityType": 0, "year": 2015}, {"date": "2015-10-11", "lng": -73.78893149999999, "lat": 40.693396500000006, "zipCode": 11433, "severityType": 0, "year": 2015}, {"date": "2015-10-11", "lng": -73.7921314, "lat": 40.694115999999994, "zipCode": 11433, "severityType": 0, "year": 2015}, {"date": "2015-10-11", "lng": -73.7812893, "lat": 40.7035489, "zipCode": 11433, "severityType": 0, "year": 2015}, {"date": "2015-10-11", "lng": -73.7840906, "lat": 40.7005294, "zipCode": 11433, "severityType": 0, "year": 2015}, {"date": "2015-10-11", "lng": -73.78488940000001, "lat": 40.6966251, "zipCode": 11433, "severityType": 0, "year": 2015}, {"date": "2015-10-09", "lng": -73.785848, "lat": 40.7001978, "zipCode": 11433, "severityType": 0, "year": 2015}, {"date": "2015-10-08", "lng": -73.782771, "lat": 40.6959953, "zipCode": 11433, "severityType": 1, "year": 2015}, {"date": "2015-10-08", "lng": -73.79572259999999, "lat": 40.6990136, "zipCode": 11433, "severityType": 0, "year": 2015}, {"date": "2015-10-08", "lng": -73.79405320000001, "lat": 40.69537929999999, "zipCode": 11433, "severityType": 0, "year": 2015}, {"date": "2015-10-08", "lng": -73.79379200000001, "lat": 40.704033100000004, "zipCode": 11433, "severityType": 0, "year": 2015}, {"date": "2015-10-08", "lng": -73.7943413, "lat": 40.693178499999995, "zipCode": 11433, "severityType": 0, "year": 2015}, {"date": "2015-10-07", "lng": -73.79165429999999, "lat": 40.7048554, "zipCode": 11433, "severityType": 0, "year": 2015}, {"date": "2015-10-07", "lng": -73.79165429999999, "lat": 40.7048554, "zipCode": 11433, "severityType": 1, "year": 2015}, {"date": "2015-10-06", "lng": -73.79165429999999, "lat": 40.7048554, "zipCode": 11433, "severityType": 0, "year": 2015}, {"date": "2015-10-06", "lng": -73.794641, "lat": 40.70123770000001, "zipCode": 11433, "severityType": 0, "year": 2015}, {"date": "2015-10-06", "lng": -73.794641, "lat": 40.70123770000001, "zipCode": 11433, "severityType": 0, "year": 2015}, {"date": "2015-10-05", "lng": -73.7844195, "lat": 40.7047625, "zipCode": 11433, "severityType": 0, "year": 2015}, {"date": "2015-10-04", "lng": -73.7950864, "lat": 40.6912777, "zipCode": 11433, "severityType": 0, "year": 2015}, {"date": "2015-10-03", "lng": -73.7784896, "lat": 40.7038345, "zipCode": 11433, "severityType": 0, "year": 2015}, {"date": "2015-10-02", "lng": -73.783825, "lat": 40.7079288, "zipCode": 11433, "severityType": 0, "year": 2015}, {"date": "2015-10-01", "lng": -73.7960918, "lat": 40.7032933, "zipCode": 11433, "severityType": 0, "year": 2015}, {"date": "2015-10-01", "lng": -73.79239129999999, "lat": 40.70216679999999, "zipCode": 11433, "severityType": 0, "year": 2015}, {"date": "2015-09-30", "lng": -73.7790802, "lat": 40.6975638, "zipCode": 11433, "severityType": 0, "year": 2015}, {"date": "2015-09-29", "lng": -73.7828868, "lat": 40.7069472, "zipCode": 11433, "severityType": 0, "year": 2015}, {"date": "2015-09-29", "lng": -73.7825671, "lat": 40.705426, "zipCode": 11433, "severityType": 0, "year": 2015}, {"date": "2015-09-29", "lng": -73.78348670000001, "lat": 40.696584, "zipCode": 11433, "severityType": 0, "year": 2015}, {"date": "2015-09-29", "lng": -73.7739552, "lat": 40.6998045, "zipCode": 11433, "severityType": 0, "year": 2015}, {"date": "2015-09-29", "lng": -73.7883472, "lat": 40.688880299999994, "zipCode": 11433, "severityType": 0, "year": 2015}, {"date": "2015-09-29", "lng": -73.79026529999999, "lat": 40.7015564, "zipCode": 11433, "severityType": 0, "year": 2015}, {"date": "2015-09-26", "lng": -73.79677109999999, "lat": 40.7005141, "zipCode": 11433, "severityType": 0, "year": 2015}, {"date": "2015-09-26", "lng": -73.7866075, "lat": 40.6961589, "zipCode": 11433, "severityType": 0, "year": 2015}, {"date": "2015-09-26", "lng": -73.7866075, "lat": 40.6961589, "zipCode": 11433, "severityType": 0, "year": 2015}, {"date": "2015-09-25", "lng": -73.7928495, "lat": 40.7044239, "zipCode": 11433, "severityType": 0, "year": 2015}, {"date": "2015-09-24", "lng": -73.7928495, "lat": 40.7044239, "zipCode": 11433, "severityType": 0, "year": 2015}, {"date": "2015-09-24", "lng": -73.78439350000001, "lat": 40.696091700000004, "zipCode": 11433, "severityType": 0, "year": 2015}, {"date": "2015-09-24", "lng": -73.7933174, "lat": 40.6977604, "zipCode": 11433, "severityType": 0, "year": 2015}, {"date": "2015-09-23", "lng": -73.7790802, "lat": 40.6975638, "zipCode": 11433, "severityType": 0, "year": 2015}, {"date": "2015-09-23", "lng": -73.78516440000001, "lat": 40.7064025, "zipCode": 11433, "severityType": 0, "year": 2015}, {"date": "2015-09-22", "lng": -73.78146329999998, "lat": 40.694469500000004, "zipCode": 11433, "severityType": 1, "year": 2015}, {"date": "2015-09-22", "lng": -73.7920324, "lat": 40.6900123, "zipCode": 11433, "severityType": 0, "year": 2015}, {"date": "2015-09-22", "lng": -73.79712409999999, "lat": 40.7030344, "zipCode": 11433, "severityType": 0, "year": 2015}, {"date": "2015-09-21", "lng": -73.7907968, "lat": 40.698818100000004, "zipCode": 11433, "severityType": 0, "year": 2015}, {"date": "2015-09-20", "lng": -73.7942116, "lat": 40.69897520000001, "zipCode": 11433, "severityType": 0, "year": 2015}, {"date": "2015-09-19", "lng": -73.7825671, "lat": 40.705426, "zipCode": 11433, "severityType": 0, "year": 2015}, {"date": "2015-09-19", "lng": -73.786332, "lat": 40.689839899999996, "zipCode": 11433, "severityType": 0, "year": 2015}, {"date": "2015-09-19", "lng": -73.783825, "lat": 40.7079288, "zipCode": 11433, "severityType": 0, "year": 2015}, {"date": "2015-09-18", "lng": -73.79379200000001, "lat": 40.704033100000004, "zipCode": 11433, "severityType": 0, "year": 2015}, {"date": "2015-09-17", "lng": -73.78146329999998, "lat": 40.694469500000004, "zipCode": 11433, "severityType": 0, "year": 2015}, {"date": "2015-09-17", "lng": -73.794641, "lat": 40.70123770000001, "zipCode": 11433, "severityType": 0, "year": 2015}, {"date": "2015-09-17", "lng": -73.79076529999999, "lat": 40.7019827, "zipCode": 11433, "severityType": 0, "year": 2015}, {"date": "2015-09-16", "lng": -73.78146329999998, "lat": 40.694469500000004, "zipCode": 11433, "severityType": 0, "year": 2015}, {"date": "2015-09-16", "lng": -73.7823892, "lat": 40.7013826, "zipCode": 11433, "severityType": 0, "year": 2015}, {"date": "2015-09-16", "lng": -73.7960918, "lat": 40.7032933, "zipCode": 11433, "severityType": 0, "year": 2015}, {"date": "2015-09-15", "lng": -73.7891925, "lat": 40.703204, "zipCode": 11433, "severityType": 0, "year": 2015}, {"date": "2015-09-15", "lng": -73.79008759999999, "lat": 40.6949823, "zipCode": 11433, "severityType": 0, "year": 2015}, {"date": "2015-09-15", "lng": -73.787009, "lat": 40.696909000000005, "zipCode": 11433, "severityType": 0, "year": 2015}, {"date": "2015-09-15", "lng": -73.79572259999999, "lat": 40.6990136, "zipCode": 11433, "severityType": 0, "year": 2015}, {"date": "2015-09-14", "lng": -73.78609509999998, "lat": 40.689501899999996, "zipCode": 11433, "severityType": 0, "year": 2015}, {"date": "2015-09-13", "lng": -73.7883472, "lat": 40.688880299999994, "zipCode": 11433, "severityType": 0, "year": 2015}, {"date": "2015-09-12", "lng": -73.7895391, "lat": 40.7008222, "zipCode": 11433, "severityType": 0, "year": 2015}, {"date": "2015-09-12", "lng": -73.7812893, "lat": 40.7035489, "zipCode": 11433, "severityType": 0, "year": 2015}, {"date": "2015-09-12", "lng": -73.7943413, "lat": 40.693178499999995, "zipCode": 11433, "severityType": 0, "year": 2015}, {"date": "2015-09-12", "lng": -73.79572259999999, "lat": 40.6990136, "zipCode": 11433, "severityType": 0, "year": 2015}, {"date": "2015-09-11", "lng": -73.79026529999999, "lat": 40.7015564, "zipCode": 11433, "severityType": 0, "year": 2015}, {"date": "2015-09-11", "lng": -73.7906942, "lat": 40.7050924, "zipCode": 11433, "severityType": 0, "year": 2015}, {"date": "2015-09-10", "lng": -73.782771, "lat": 40.6959953, "zipCode": 11433, "severityType": 0, "year": 2015}, {"date": "2015-09-10", "lng": -73.79379200000001, "lat": 40.704033100000004, "zipCode": 11433, "severityType": 1, "year": 2015}, {"date": "2015-09-10", "lng": -73.78147779999999, "lat": 40.705454100000004, "zipCode": 11433, "severityType": 0, "year": 2015}, {"date": "2015-09-10", "lng": -73.79239129999999, "lat": 40.70216679999999, "zipCode": 11433, "severityType": 0, "year": 2015}, {"date": "2015-09-10", "lng": -73.7888123, "lat": 40.6934539, "zipCode": 11433, "severityType": 0, "year": 2015}, {"date": "2015-09-09", "lng": -73.791937, "lat": 40.703253000000004, "zipCode": 11433, "severityType": 0, "year": 2015}, {"date": "2015-09-09", "lng": -73.7866075, "lat": 40.6961589, "zipCode": 11433, "severityType": 0, "year": 2015}, {"date": "2015-09-09", "lng": -73.8018952, "lat": 40.701969500000004, "zipCode": 11433, "severityType": 0, "year": 2015}, {"date": "2015-09-09", "lng": -73.7920324, "lat": 40.6900123, "zipCode": 11433, "severityType": 0, "year": 2015}, {"date": "2015-09-07", "lng": -73.794641, "lat": 40.70123770000001, "zipCode": 11433, "severityType": 0, "year": 2015}, {"date": "2015-09-07", "lng": -73.7891639, "lat": 40.697448200000004, "zipCode": 11433, "severityType": 0, "year": 2015}, {"date": "2015-09-07", "lng": -73.7987681, "lat": 40.694857899999995, "zipCode": 11433, "severityType": 0, "year": 2015}, {"date": "2015-09-06", "lng": -73.7947704, "lat": 40.6908434, "zipCode": 11433, "severityType": 0, "year": 2015}, {"date": "2015-09-05", "lng": -73.79008759999999, "lat": 40.6949823, "zipCode": 11433, "severityType": 0, "year": 2015}, {"date": "2015-09-05", "lng": -73.7802385, "lat": 40.6929712, "zipCode": 11433, "severityType": 0, "year": 2015}, {"date": "2015-09-05", "lng": -73.79026529999999, "lat": 40.7015564, "zipCode": 11433, "severityType": 1, "year": 2015}, {"date": "2015-09-05", "lng": -73.7943413, "lat": 40.693178499999995, "zipCode": 11433, "severityType": 0, "year": 2015}, {"date": "2015-09-03", "lng": -73.79572259999999, "lat": 40.6990136, "zipCode": 11433, "severityType": 1, "year": 2015}, {"date": "2015-09-01", "lng": -73.79712409999999, "lat": 40.7030344, "zipCode": 11433, "severityType": 0, "year": 2015}, {"date": "2015-09-01", "lng": -73.80210109999999, "lat": 40.7006414, "zipCode": 11433, "severityType": 0, "year": 2015}, {"date": "2015-09-01", "lng": -73.77943940000002, "lat": 40.693644899999995, "zipCode": 11433, "severityType": 0, "year": 2015}, {"date": "2015-09-01", "lng": -73.79677109999999, "lat": 40.7005141, "zipCode": 11433, "severityType": 0, "year": 2015}, {"date": "2015-09-01", "lng": -73.78269559999998, "lat": 40.6981059, "zipCode": 11433, "severityType": 1, "year": 2015}, {"date": "2015-08-31", "lng": -73.7960918, "lat": 40.7032933, "zipCode": 11433, "severityType": 0, "year": 2015}, {"date": "2015-08-31", "lng": -73.7891925, "lat": 40.703204, "zipCode": 11433, "severityType": 0, "year": 2015}, {"date": "2015-08-31", "lng": -73.79240379999999, "lat": 40.6981513, "zipCode": 11433, "severityType": 0, "year": 2015}, {"date": "2015-08-31", "lng": -73.7896405, "lat": 40.697246, "zipCode": 11433, "severityType": 0, "year": 2015}, {"date": "2015-08-30", "lng": -73.7960918, "lat": 40.7032933, "zipCode": 11433, "severityType": 0, "year": 2015}, {"date": "2015-08-30", "lng": -73.7960918, "lat": 40.7032933, "zipCode": 11433, "severityType": 1, "year": 2015}, {"date": "2015-08-29", "lng": -73.7820264, "lat": 40.702029700000004, "zipCode": 11433, "severityType": 0, "year": 2015}, {"date": "2015-08-29", "lng": -73.7986849, "lat": 40.699715999999995, "zipCode": 11433, "severityType": 0, "year": 2015}, {"date": "2015-08-28", "lng": -73.7912475, "lat": 40.6965654, "zipCode": 11433, "severityType": 0, "year": 2015}, {"date": "2015-08-28", "lng": -73.7963245, "lat": 40.6944171, "zipCode": 11433, "severityType": 1, "year": 2015}, {"date": "2015-08-27", "lng": -73.80210109999999, "lat": 40.7006414, "zipCode": 11433, "severityType": 0, "year": 2015}, {"date": "2015-08-27", "lng": -73.79449890000001, "lat": 40.6993847, "zipCode": 11433, "severityType": 0, "year": 2015}, {"date": "2015-08-27", "lng": -73.7828355, "lat": 40.693895700000006, "zipCode": 11433, "severityType": 0, "year": 2015}, {"date": "2015-08-27", "lng": -73.7984161, "lat": 40.7027402, "zipCode": 11433, "severityType": 0, "year": 2015}, {"date": "2015-08-27", "lng": -73.7784896, "lat": 40.7038345, "zipCode": 11433, "severityType": 0, "year": 2015}, {"date": "2015-08-27", "lng": -73.80210109999999, "lat": 40.7006414, "zipCode": 11433, "severityType": 0, "year": 2015}, {"date": "2015-08-26", "lng": -73.7960918, "lat": 40.7032933, "zipCode": 11433, "severityType": 0, "year": 2015}, {"date": "2015-08-26", "lng": -73.7978607, "lat": 40.6979935, "zipCode": 11433, "severityType": 0, "year": 2015}, {"date": "2015-08-25", "lng": -73.79239129999999, "lat": 40.70216679999999, "zipCode": 11433, "severityType": 0, "year": 2015}, {"date": "2015-08-24", "lng": -73.78284520000001, "lat": 40.69976679999999, "zipCode": 11433, "severityType": 0, "year": 2015}, {"date": "2015-08-23", "lng": -73.7960918, "lat": 40.7032933, "zipCode": 11433, "severityType": 0, "year": 2015}, {"date": "2015-08-22", "lng": -73.7910048, "lat": 40.694594200000004, "zipCode": 11433, "severityType": 0, "year": 2015}, {"date": "2015-08-22", "lng": -73.7802385, "lat": 40.6929712, "zipCode": 11433, "severityType": 0, "year": 2015}, {"date": "2015-08-22", "lng": -73.7912475, "lat": 40.6965654, "zipCode": 11433, "severityType": 0, "year": 2015}, {"date": "2015-08-21", "lng": -73.79240379999999, "lat": 40.6981513, "zipCode": 11433, "severityType": 0, "year": 2015}, {"date": "2015-08-21", "lng": -73.7867213, "lat": 40.7000348, "zipCode": 11433, "severityType": 0, "year": 2015}, {"date": "2015-08-21", "lng": -73.7833297, "lat": 40.69162120000001, "zipCode": 11433, "severityType": 0, "year": 2015}, {"date": "2015-08-21", "lng": -73.79026529999999, "lat": 40.7015564, "zipCode": 11433, "severityType": 0, "year": 2015}, {"date": "2015-08-17", "lng": -73.7890285, "lat": 40.700327200000004, "zipCode": 11433, "severityType": 0, "year": 2015}, {"date": "2015-08-17", "lng": -73.7825671, "lat": 40.705426, "zipCode": 11433, "severityType": 0, "year": 2015}, {"date": "2015-08-17", "lng": -73.7933174, "lat": 40.6977604, "zipCode": 11433, "severityType": 0, "year": 2015}, {"date": "2015-08-16", "lng": -73.79357809999999, "lat": 40.6997563, "zipCode": 11433, "severityType": 0, "year": 2015}, {"date": "2015-08-16", "lng": -73.7793745, "lat": 40.7078133, "zipCode": 11433, "severityType": 0, "year": 2015}, {"date": "2015-08-15", "lng": -73.7808694, "lat": 40.7029113, "zipCode": 11433, "severityType": 0, "year": 2015}, {"date": "2015-08-14", "lng": -73.79550479999999, "lat": 40.694764299999996, "zipCode": 11433, "severityType": 0, "year": 2015}, {"date": "2015-08-13", "lng": -73.7802385, "lat": 40.6929712, "zipCode": 11433, "severityType": 0, "year": 2015}, {"date": "2015-08-13", "lng": -73.77748340000001, "lat": 40.6930016, "zipCode": 11433, "severityType": 0, "year": 2015}, {"date": "2015-08-12", "lng": -73.7978607, "lat": 40.6979935, "zipCode": 11433, "severityType": 0, "year": 2015}, {"date": "2015-08-12", "lng": -73.7978607, "lat": 40.6979935, "zipCode": 11433, "severityType": 0, "year": 2015}, {"date": "2015-08-11", "lng": -73.7960918, "lat": 40.7032933, "zipCode": 11433, "severityType": 0, "year": 2015}, {"date": "2015-08-11", "lng": -73.7999209, "lat": 40.7024739, "zipCode": 11433, "severityType": 0, "year": 2015}, {"date": "2015-08-10", "lng": -73.79008759999999, "lat": 40.6949823, "zipCode": 11433, "severityType": 0, "year": 2015}, {"date": "2015-08-10", "lng": -73.7960918, "lat": 40.7032933, "zipCode": 11433, "severityType": 0, "year": 2015}, {"date": "2015-08-10", "lng": -73.79165429999999, "lat": 40.7048554, "zipCode": 11433, "severityType": 1, "year": 2015}, {"date": "2015-08-10", "lng": -73.7805483, "lat": 40.7084277, "zipCode": 11433, "severityType": 0, "year": 2015}, {"date": "2015-08-09", "lng": -73.78751740000001, "lat": 40.70371420000001, "zipCode": 11433, "severityType": 0, "year": 2015}, {"date": "2015-08-09", "lng": -73.7928933, "lat": 40.6937907, "zipCode": 11433, "severityType": 0, "year": 2015}, {"date": "2015-08-09", "lng": -73.79239129999999, "lat": 40.70216679999999, "zipCode": 11433, "severityType": 0, "year": 2015}, {"date": "2015-08-08", "lng": -73.7865546, "lat": 40.69014779999999, "zipCode": 11433, "severityType": 0, "year": 2015}, {"date": "2015-08-08", "lng": -73.7881046, "lat": 40.6937326, "zipCode": 11433, "severityType": 0, "year": 2015}, {"date": "2015-08-08", "lng": -73.7789147, "lat": 40.7017959, "zipCode": 11433, "severityType": 0, "year": 2015}, {"date": "2015-08-08", "lng": -73.7802385, "lat": 40.6929712, "zipCode": 11433, "severityType": 0, "year": 2015}, {"date": "2015-08-08", "lng": -73.7802385, "lat": 40.6929712, "zipCode": 11433, "severityType": 0, "year": 2015}, {"date": "2015-08-07", "lng": -73.7825671, "lat": 40.705426, "zipCode": 11433, "severityType": 0, "year": 2015}, {"date": "2015-08-07", "lng": -73.7849603, "lat": 40.7003636, "zipCode": 11433, "severityType": 0, "year": 2015}, {"date": "2015-08-07", "lng": -73.794641, "lat": 40.70123770000001, "zipCode": 11433, "severityType": 0, "year": 2015}, {"date": "2015-08-06", "lng": -73.7999209, "lat": 40.7024739, "zipCode": 11433, "severityType": 0, "year": 2015}, {"date": "2015-08-04", "lng": -73.77792059999999, "lat": 40.695980600000006, "zipCode": 11433, "severityType": 0, "year": 2015}, {"date": "2015-08-03", "lng": -73.79954129999999, "lat": 40.699160299999996, "zipCode": 11433, "severityType": 0, "year": 2015}, {"date": "2015-08-03", "lng": -73.799184, "lat": 40.6968705, "zipCode": 11433, "severityType": 0, "year": 2015}, {"date": "2015-08-02", "lng": -73.7834921, "lat": 40.7026994, "zipCode": 11433, "severityType": 0, "year": 2015}, {"date": "2015-08-02", "lng": -73.7899943, "lat": 40.7028706, "zipCode": 11433, "severityType": 0, "year": 2015}, {"date": "2015-08-02", "lng": -73.7866075, "lat": 40.6961589, "zipCode": 11433, "severityType": 0, "year": 2015}, {"date": "2015-08-01", "lng": -73.7913825, "lat": 40.6902856, "zipCode": 11433, "severityType": 1, "year": 2015}, {"date": "2015-08-01", "lng": -73.78597950000001, "lat": 40.7041862, "zipCode": 11433, "severityType": 0, "year": 2015}, {"date": "2015-08-01", "lng": -73.78733740000001, "lat": 40.705868599999995, "zipCode": 11433, "severityType": 0, "year": 2015}, {"date": "2015-08-01", "lng": -73.78884980000001, "lat": 40.7055035, "zipCode": 11433, "severityType": 0, "year": 2015}, {"date": "2015-08-01", "lng": -73.7928444, "lat": 40.7002436, "zipCode": 11433, "severityType": 0, "year": 2015}, {"date": "2015-08-01", "lng": -73.799184, "lat": 40.6968705, "zipCode": 11433, "severityType": 0, "year": 2015}, {"date": "2015-07-31", "lng": -73.7834279, "lat": 40.694701, "zipCode": 11433, "severityType": 0, "year": 2015}, {"date": "2015-07-31", "lng": -73.78893149999999, "lat": 40.693396500000006, "zipCode": 11433, "severityType": 0, "year": 2015}, {"date": "2015-07-30", "lng": -73.7910239, "lat": 40.7057792, "zipCode": 11433, "severityType": 0, "year": 2015}, {"date": "2015-07-29", "lng": -73.7912475, "lat": 40.6965654, "zipCode": 11433, "severityType": 0, "year": 2015}, {"date": "2015-07-29", "lng": -73.7802385, "lat": 40.6929712, "zipCode": 11433, "severityType": 0, "year": 2015}, {"date": "2015-07-29", "lng": -73.7971441, "lat": 40.69407, "zipCode": 11433, "severityType": 0, "year": 2015}, {"date": "2015-07-28", "lng": -73.7895391, "lat": 40.7008222, "zipCode": 11433, "severityType": 0, "year": 2015}, {"date": "2015-07-28", "lng": -73.79239129999999, "lat": 40.70216679999999, "zipCode": 11433, "severityType": 0, "year": 2015}, {"date": "2015-07-28", "lng": -73.78605959999999, "lat": 40.706181799999996, "zipCode": 11433, "severityType": 0, "year": 2015}, {"date": "2015-07-27", "lng": -73.7984161, "lat": 40.7027402, "zipCode": 11433, "severityType": 0, "year": 2015}, {"date": "2015-07-26", "lng": -73.79240379999999, "lat": 40.6981513, "zipCode": 11433, "severityType": 0, "year": 2015}, {"date": "2015-07-26", "lng": -73.782771, "lat": 40.6959953, "zipCode": 11433, "severityType": 0, "year": 2015}, {"date": "2015-07-26", "lng": -73.78597950000001, "lat": 40.7041862, "zipCode": 11433, "severityType": 0, "year": 2015}, {"date": "2015-07-26", "lng": -73.78893149999999, "lat": 40.693396500000006, "zipCode": 11433, "severityType": 0, "year": 2015}, {"date": "2015-07-25", "lng": -73.8010546, "lat": 40.6984191, "zipCode": 11433, "severityType": 0, "year": 2015}, {"date": "2015-07-25", "lng": -73.7802385, "lat": 40.6929712, "zipCode": 11433, "severityType": 0, "year": 2015}, {"date": "2015-07-24", "lng": -73.7895391, "lat": 40.7008222, "zipCode": 11433, "severityType": 0, "year": 2015}, {"date": "2015-07-23", "lng": -73.79165429999999, "lat": 40.7048554, "zipCode": 11433, "severityType": 0, "year": 2015}, {"date": "2015-07-23", "lng": -73.7960918, "lat": 40.7032933, "zipCode": 11433, "severityType": 0, "year": 2015}, {"date": "2015-07-23", "lng": -73.7874917, "lat": 40.6914231, "zipCode": 11433, "severityType": 0, "year": 2015}, {"date": "2015-07-22", "lng": -73.78146329999998, "lat": 40.694469500000004, "zipCode": 11433, "severityType": 0, "year": 2015}, {"date": "2015-07-22", "lng": -73.79318149999999, "lat": 40.691584399999996, "zipCode": 11433, "severityType": 0, "year": 2015}, {"date": "2015-07-22", "lng": -73.7912475, "lat": 40.6965654, "zipCode": 11433, "severityType": 0, "year": 2015}, {"date": "2015-07-22", "lng": -73.777836, "lat": 40.6943226, "zipCode": 11433, "severityType": 0, "year": 2015}, {"date": "2015-07-22", "lng": -73.7909536, "lat": 40.6925273, "zipCode": 11433, "severityType": 0, "year": 2015}, {"date": "2015-07-22", "lng": -73.79239129999999, "lat": 40.70216679999999, "zipCode": 11433, "severityType": 0, "year": 2015}, {"date": "2015-07-21", "lng": -73.78597950000001, "lat": 40.7041862, "zipCode": 11433, "severityType": 0, "year": 2015}, {"date": "2015-07-21", "lng": -73.79026529999999, "lat": 40.7015564, "zipCode": 11433, "severityType": 0, "year": 2015}, {"date": "2015-07-21", "lng": -73.7928495, "lat": 40.7044239, "zipCode": 11433, "severityType": 0, "year": 2015}, {"date": "2015-07-20", "lng": -73.7984161, "lat": 40.7027402, "zipCode": 11433, "severityType": 0, "year": 2015}, {"date": "2015-07-19", "lng": -73.7971441, "lat": 40.69407, "zipCode": 11433, "severityType": 0, "year": 2015}, {"date": "2015-07-19", "lng": -73.7740213, "lat": 40.6962639, "zipCode": 11433, "severityType": 1, "year": 2015}, {"date": "2015-07-19", "lng": -73.78529820000001, "lat": 40.6928573, "zipCode": 11433, "severityType": 0, "year": 2015}, {"date": "2015-07-18", "lng": -73.7933174, "lat": 40.6977604, "zipCode": 11433, "severityType": 0, "year": 2015}, {"date": "2015-07-17", "lng": -73.8010546, "lat": 40.6984191, "zipCode": 11433, "severityType": 0, "year": 2015}, {"date": "2015-07-17", "lng": -73.777836, "lat": 40.6943226, "zipCode": 11433, "severityType": 0, "year": 2015}, {"date": "2015-07-17", "lng": -73.7844078, "lat": 40.703933500000005, "zipCode": 11433, "severityType": 0, "year": 2015}, {"date": "2015-07-17", "lng": -73.7928444, "lat": 40.7002436, "zipCode": 11433, "severityType": 0, "year": 2015}, {"date": "2015-07-16", "lng": -73.7845949, "lat": 40.7051827, "zipCode": 11433, "severityType": 0, "year": 2015}, {"date": "2015-07-16", "lng": -73.7960918, "lat": 40.7032933, "zipCode": 11433, "severityType": 1, "year": 2015}, {"date": "2015-07-15", "lng": -73.7972118, "lat": 40.691962100000005, "zipCode": 11433, "severityType": 0, "year": 2015}, {"date": "2015-07-15", "lng": -73.8024077, "lat": 40.7018524, "zipCode": 11433, "severityType": 0, "year": 2015}, {"date": "2015-07-14", "lng": -73.7842729, "lat": 40.7066177, "zipCode": 11433, "severityType": 0, "year": 2015}, {"date": "2015-07-14", "lng": -73.78487209999999, "lat": 40.697519899999996, "zipCode": 11433, "severityType": 0, "year": 2015}, {"date": "2015-07-14", "lng": -73.7831407, "lat": 40.7020702, "zipCode": 11433, "severityType": 0, "year": 2015}, {"date": "2015-07-13", "lng": -73.7920324, "lat": 40.6900123, "zipCode": 11433, "severityType": 0, "year": 2015}, {"date": "2015-07-13", "lng": -73.7978607, "lat": 40.6979935, "zipCode": 11433, "severityType": 0, "year": 2015}, {"date": "2015-07-12", "lng": -73.78488940000001, "lat": 40.6966251, "zipCode": 11433, "severityType": 0, "year": 2015}, {"date": "2015-07-12", "lng": -73.7848493, "lat": 40.7045849, "zipCode": 11433, "severityType": 0, "year": 2015}, {"date": "2015-07-12", "lng": -73.7991021, "lat": 40.6953141, "zipCode": 11433, "severityType": 0, "year": 2015}, {"date": "2015-07-11", "lng": -73.7920324, "lat": 40.6900123, "zipCode": 11433, "severityType": 0, "year": 2015}, {"date": "2015-07-11", "lng": -73.78449300000001, "lat": 40.6931989, "zipCode": 11433, "severityType": 0, "year": 2015}, {"date": "2015-07-10", "lng": -73.7984161, "lat": 40.7027402, "zipCode": 11433, "severityType": 0, "year": 2015}, {"date": "2015-07-10", "lng": -73.79239129999999, "lat": 40.70216679999999, "zipCode": 11433, "severityType": 0, "year": 2015}, {"date": "2015-07-10", "lng": -73.78023979999999, "lat": 40.69914970000001, "zipCode": 11433, "severityType": 0, "year": 2015}, {"date": "2015-07-09", "lng": -73.78733740000001, "lat": 40.705868599999995, "zipCode": 11433, "severityType": 0, "year": 2015}, {"date": "2015-07-07", "lng": -73.78609509999998, "lat": 40.689501899999996, "zipCode": 11433, "severityType": 0, "year": 2015}, {"date": "2015-07-07", "lng": -73.7978607, "lat": 40.6979935, "zipCode": 11433, "severityType": 0, "year": 2015}, {"date": "2015-07-07", "lng": -73.7895391, "lat": 40.7008222, "zipCode": 11433, "severityType": 0, "year": 2015}, {"date": "2015-07-06", "lng": -73.79239129999999, "lat": 40.70216679999999, "zipCode": 11433, "severityType": 0, "year": 2015}, {"date": "2015-07-06", "lng": -73.7972118, "lat": 40.691962100000005, "zipCode": 11433, "severityType": 0, "year": 2015}, {"date": "2015-07-06", "lng": -73.782771, "lat": 40.6959953, "zipCode": 11433, "severityType": 0, "year": 2015}, {"date": "2015-07-06", "lng": -73.790862, "lat": 40.688407299999994, "zipCode": 11433, "severityType": 0, "year": 2015}, {"date": "2015-07-05", "lng": -73.7928495, "lat": 40.7044239, "zipCode": 11433, "severityType": 0, "year": 2015}, {"date": "2015-07-04", "lng": -73.7825671, "lat": 40.705426, "zipCode": 11433, "severityType": 0, "year": 2015}, {"date": "2015-07-03", "lng": -73.7912475, "lat": 40.6965654, "zipCode": 11433, "severityType": 0, "year": 2015}, {"date": "2015-07-03", "lng": -73.77846059999999, "lat": 40.6940904, "zipCode": 11433, "severityType": 0, "year": 2015}, {"date": "2015-07-02", "lng": -73.78609509999998, "lat": 40.689501899999996, "zipCode": 11433, "severityType": 0, "year": 2015}, {"date": "2015-07-01", "lng": -73.8010546, "lat": 40.6984191, "zipCode": 11433, "severityType": 0, "year": 2015}, {"date": "2015-07-01", "lng": -73.7874917, "lat": 40.6914231, "zipCode": 11433, "severityType": 0, "year": 2015}, {"date": "2015-07-01", "lng": -73.8024077, "lat": 40.7018524, "zipCode": 11433, "severityType": 0, "year": 2015}, {"date": "2015-07-01", "lng": -73.794641, "lat": 40.70123770000001, "zipCode": 11433, "severityType": 0, "year": 2015}, {"date": "2015-06-30", "lng": -73.7823892, "lat": 40.7013826, "zipCode": 11433, "severityType": 0, "year": 2015}, {"date": "2015-06-30", "lng": -73.7844195, "lat": 40.7047625, "zipCode": 11433, "severityType": 0, "year": 2015}, {"date": "2015-06-29", "lng": -73.79165429999999, "lat": 40.7048554, "zipCode": 11433, "severityType": 0, "year": 2015}, {"date": "2015-06-29", "lng": -73.79379200000001, "lat": 40.704033100000004, "zipCode": 11433, "severityType": 0, "year": 2015}, {"date": "2015-06-29", "lng": -73.78337049999999, "lat": 40.7068328, "zipCode": 11433, "severityType": 0, "year": 2015}, {"date": "2015-06-29", "lng": -73.78337049999999, "lat": 40.7068328, "zipCode": 11433, "severityType": 0, "year": 2015}, {"date": "2015-06-27", "lng": -73.7920324, "lat": 40.6900123, "zipCode": 11433, "severityType": 0, "year": 2015}, {"date": "2015-06-26", "lng": -73.7960918, "lat": 40.7032933, "zipCode": 11433, "severityType": 0, "year": 2015}, {"date": "2015-06-26", "lng": -73.78337049999999, "lat": 40.7068328, "zipCode": 11433, "severityType": 0, "year": 2015}, {"date": "2015-06-26", "lng": -73.7848493, "lat": 40.7045849, "zipCode": 11433, "severityType": 0, "year": 2015}, {"date": "2015-06-25", "lng": -73.8018952, "lat": 40.701969500000004, "zipCode": 11433, "severityType": 0, "year": 2015}, {"date": "2015-06-25", "lng": -73.78733740000001, "lat": 40.705868599999995, "zipCode": 11433, "severityType": 0, "year": 2015}, {"date": "2015-06-24", "lng": -73.79076529999999, "lat": 40.7019827, "zipCode": 11433, "severityType": 0, "year": 2015}, {"date": "2015-06-24", "lng": -73.794641, "lat": 40.70123770000001, "zipCode": 11433, "severityType": 0, "year": 2015}, {"date": "2015-06-24", "lng": -73.7873116, "lat": 40.70154, "zipCode": 11433, "severityType": 1, "year": 2015}, {"date": "2015-06-21", "lng": -73.78146329999998, "lat": 40.694469500000004, "zipCode": 11433, "severityType": 0, "year": 2015}, {"date": "2015-06-20", "lng": -73.7984161, "lat": 40.7027402, "zipCode": 11433, "severityType": 0, "year": 2015}, {"date": "2015-06-20", "lng": -73.794641, "lat": 40.70123770000001, "zipCode": 11433, "severityType": 0, "year": 2015}, {"date": "2015-06-19", "lng": -73.7928495, "lat": 40.7044239, "zipCode": 11433, "severityType": 0, "year": 2015}, {"date": "2015-06-19", "lng": -73.7967665, "lat": 40.69135479999999, "zipCode": 11433, "severityType": 0, "year": 2015}, {"date": "2015-06-18", "lng": -73.799184, "lat": 40.6968705, "zipCode": 11433, "severityType": 0, "year": 2015}, {"date": "2015-06-18", "lng": -73.79712409999999, "lat": 40.7030344, "zipCode": 11433, "severityType": 1, "year": 2015}, {"date": "2015-06-18", "lng": -73.78778249999999, "lat": 40.6918189, "zipCode": 11433, "severityType": 0, "year": 2015}, {"date": "2015-06-18", "lng": -73.79712409999999, "lat": 40.7030344, "zipCode": 11433, "severityType": 0, "year": 2015}, {"date": "2015-06-18", "lng": -73.791584, "lat": 40.6984956, "zipCode": 11433, "severityType": 0, "year": 2015}, {"date": "2015-06-17", "lng": -73.78884980000001, "lat": 40.7055035, "zipCode": 11433, "severityType": 1, "year": 2015}, {"date": "2015-06-17", "lng": -73.7761876, "lat": 40.6965756, "zipCode": 11433, "severityType": 0, "year": 2015}, {"date": "2015-06-16", "lng": -73.79239129999999, "lat": 40.70216679999999, "zipCode": 11433, "severityType": 1, "year": 2015}, {"date": "2015-06-16", "lng": -73.7912475, "lat": 40.6965654, "zipCode": 11433, "severityType": 0, "year": 2015}, {"date": "2015-06-15", "lng": -73.78250279999999, "lat": 40.691968200000005, "zipCode": 11433, "severityType": 0, "year": 2015}, {"date": "2015-06-13", "lng": -73.78153950000001, "lat": 40.6965227, "zipCode": 11433, "severityType": 0, "year": 2015}, {"date": "2015-06-13", "lng": -73.77826400000001, "lat": 40.697910799999995, "zipCode": 11433, "severityType": 0, "year": 2015}, {"date": "2015-06-12", "lng": -73.7784896, "lat": 40.7038345, "zipCode": 11433, "severityType": 0, "year": 2015}, {"date": "2015-06-12", "lng": -73.7949963, "lat": 40.688917, "zipCode": 11433, "severityType": 0, "year": 2015}, {"date": "2015-06-12", "lng": -73.7949963, "lat": 40.688917, "zipCode": 11433, "severityType": 0, "year": 2015}, {"date": "2015-06-12", "lng": -73.7848493, "lat": 40.7045849, "zipCode": 11433, "severityType": 0, "year": 2015}, {"date": "2015-06-11", "lng": -73.7983005, "lat": 40.6956558, "zipCode": 11433, "severityType": 0, "year": 2015}, {"date": "2015-06-11", "lng": -73.7831407, "lat": 40.7020702, "zipCode": 11433, "severityType": 0, "year": 2015}, {"date": "2015-06-11", "lng": -73.8024077, "lat": 40.7018524, "zipCode": 11433, "severityType": 0, "year": 2015}, {"date": "2015-06-11", "lng": -73.7960918, "lat": 40.7032933, "zipCode": 11433, "severityType": 0, "year": 2015}, {"date": "2015-06-10", "lng": -73.7825671, "lat": 40.705426, "zipCode": 11433, "severityType": 0, "year": 2015}, {"date": "2015-06-09", "lng": -73.7910128, "lat": 40.69665560000001, "zipCode": 11433, "severityType": 0, "year": 2015}, {"date": "2015-06-07", "lng": -73.7959842, "lat": 40.6924815, "zipCode": 11433, "severityType": 0, "year": 2015}, {"date": "2015-06-07", "lng": -73.78884980000001, "lat": 40.7055035, "zipCode": 11433, "severityType": 0, "year": 2015}, {"date": "2015-06-05", "lng": -73.79449890000001, "lat": 40.6993847, "zipCode": 11433, "severityType": 0, "year": 2015}, {"date": "2015-06-05", "lng": -73.79379200000001, "lat": 40.704033100000004, "zipCode": 11433, "severityType": 0, "year": 2015}, {"date": "2015-06-05", "lng": -73.78884980000001, "lat": 40.7055035, "zipCode": 11433, "severityType": 0, "year": 2015}, {"date": "2015-06-05", "lng": -73.79379200000001, "lat": 40.704033100000004, "zipCode": 11433, "severityType": 0, "year": 2015}, {"date": "2015-06-05", "lng": -73.8024077, "lat": 40.7018524, "zipCode": 11433, "severityType": 0, "year": 2015}, {"date": "2015-06-05", "lng": -73.7873536, "lat": 40.6974064, "zipCode": 11433, "severityType": 0, "year": 2015}, {"date": "2015-06-04", "lng": -73.78488940000001, "lat": 40.6966251, "zipCode": 11433, "severityType": 0, "year": 2015}, {"date": "2015-06-03", "lng": -73.7920324, "lat": 40.6900123, "zipCode": 11433, "severityType": 0, "year": 2015}, {"date": "2015-06-03", "lng": -73.78762259999999, "lat": 40.6989989, "zipCode": 11433, "severityType": 0, "year": 2015}, {"date": "2015-06-02", "lng": -73.7891925, "lat": 40.703204, "zipCode": 11433, "severityType": 0, "year": 2015}, {"date": "2015-06-02", "lng": -73.7891613, "lat": 40.706228700000004, "zipCode": 11433, "severityType": 0, "year": 2015}, {"date": "2015-06-01", "lng": -73.7999209, "lat": 40.7024739, "zipCode": 11433, "severityType": 0, "year": 2015}, {"date": "2015-06-01", "lng": -73.782771, "lat": 40.6959953, "zipCode": 11433, "severityType": 0, "year": 2015}, {"date": "2015-06-01", "lng": -73.79712409999999, "lat": 40.7030344, "zipCode": 11433, "severityType": 0, "year": 2015}, {"date": "2015-06-01", "lng": -73.7975546, "lat": 40.700197100000004, "zipCode": 11433, "severityType": 0, "year": 2015}, {"date": "2015-05-30", "lng": -73.79042779999999, "lat": 40.6969125, "zipCode": 11433, "severityType": 0, "year": 2015}, {"date": "2015-05-29", "lng": -73.78146329999998, "lat": 40.694469500000004, "zipCode": 11433, "severityType": 0, "year": 2015}, {"date": "2015-05-29", "lng": -73.79239129999999, "lat": 40.70216679999999, "zipCode": 11433, "severityType": 0, "year": 2015}, {"date": "2015-05-29", "lng": -73.7912475, "lat": 40.6965654, "zipCode": 11433, "severityType": 0, "year": 2015}, {"date": "2015-05-28", "lng": -73.783825, "lat": 40.7079288, "zipCode": 11433, "severityType": 0, "year": 2015}, {"date": "2015-05-27", "lng": -73.7825671, "lat": 40.705426, "zipCode": 11433, "severityType": 0, "year": 2015}, {"date": "2015-05-26", "lng": -73.78146329999998, "lat": 40.694469500000004, "zipCode": 11433, "severityType": 0, "year": 2015}, {"date": "2015-05-26", "lng": -73.79240379999999, "lat": 40.6981513, "zipCode": 11433, "severityType": 0, "year": 2015}, {"date": "2015-05-25", "lng": -73.782771, "lat": 40.6959953, "zipCode": 11433, "severityType": 0, "year": 2015}, {"date": "2015-05-25", "lng": -73.79357809999999, "lat": 40.6997563, "zipCode": 11433, "severityType": 0, "year": 2015}, {"date": "2015-05-25", "lng": -73.7860344, "lat": 40.6949584, "zipCode": 11433, "severityType": 0, "year": 2015}, {"date": "2015-05-25", "lng": -73.78609509999998, "lat": 40.689501899999996, "zipCode": 11433, "severityType": 0, "year": 2015}, {"date": "2015-05-25", "lng": -73.7925589, "lat": 40.6876885, "zipCode": 11433, "severityType": 1, "year": 2015}, {"date": "2015-05-24", "lng": -73.7896405, "lat": 40.697246, "zipCode": 11433, "severityType": 0, "year": 2015}, {"date": "2015-05-24", "lng": -73.79550479999999, "lat": 40.694764299999996, "zipCode": 11433, "severityType": 0, "year": 2015}, {"date": "2015-05-23", "lng": -73.79008759999999, "lat": 40.6949823, "zipCode": 11433, "severityType": 0, "year": 2015}, {"date": "2015-05-23", "lng": -73.7870573, "lat": 40.6908294, "zipCode": 11433, "severityType": 0, "year": 2015}, {"date": "2015-05-23", "lng": -73.794641, "lat": 40.70123770000001, "zipCode": 11433, "severityType": 1, "year": 2015}, {"date": "2015-05-21", "lng": -73.7883125, "lat": 40.6907329, "zipCode": 11433, "severityType": 0, "year": 2015}, {"date": "2015-05-20", "lng": -73.79954129999999, "lat": 40.699160299999996, "zipCode": 11433, "severityType": 0, "year": 2015}, {"date": "2015-05-20", "lng": -73.7991021, "lat": 40.6953141, "zipCode": 11433, "severityType": 0, "year": 2015}, {"date": "2015-05-17", "lng": -73.78250279999999, "lat": 40.691968200000005, "zipCode": 11433, "severityType": 0, "year": 2015}, {"date": "2015-05-16", "lng": -73.78751740000001, "lat": 40.70371420000001, "zipCode": 11433, "severityType": 0, "year": 2015}, {"date": "2015-05-16", "lng": -73.7812893, "lat": 40.7035489, "zipCode": 11433, "severityType": 0, "year": 2015}, {"date": "2015-05-16", "lng": -73.7784896, "lat": 40.7038345, "zipCode": 11433, "severityType": 0, "year": 2015}, {"date": "2015-05-16", "lng": -73.7866075, "lat": 40.6961589, "zipCode": 11433, "severityType": 0, "year": 2015}, {"date": "2015-05-15", "lng": -73.78330550000001, "lat": 40.707947100000005, "zipCode": 11433, "severityType": 0, "year": 2015}, {"date": "2015-05-15", "lng": -73.7971441, "lat": 40.69407, "zipCode": 11433, "severityType": 0, "year": 2015}, {"date": "2015-05-14", "lng": -73.782771, "lat": 40.6959953, "zipCode": 11433, "severityType": 0, "year": 2015}, {"date": "2015-05-14", "lng": -73.79240379999999, "lat": 40.6981513, "zipCode": 11433, "severityType": 0, "year": 2015}, {"date": "2015-05-14", "lng": -73.7825671, "lat": 40.705426, "zipCode": 11433, "severityType": 0, "year": 2015}, {"date": "2015-05-13", "lng": -73.7983005, "lat": 40.6956558, "zipCode": 11433, "severityType": 0, "year": 2015}, {"date": "2015-05-13", "lng": -73.7975546, "lat": 40.700197100000004, "zipCode": 11433, "severityType": 0, "year": 2015}, {"date": "2015-05-11", "lng": -73.7920324, "lat": 40.6900123, "zipCode": 11433, "severityType": 0, "year": 2015}, {"date": "2015-05-10", "lng": -73.7848493, "lat": 40.7045849, "zipCode": 11433, "severityType": 0, "year": 2015}, {"date": "2015-05-09", "lng": -73.78609509999998, "lat": 40.689501899999996, "zipCode": 11433, "severityType": 0, "year": 2015}, {"date": "2015-05-09", "lng": -73.7891639, "lat": 40.697448200000004, "zipCode": 11433, "severityType": 0, "year": 2015}, {"date": "2015-05-08", "lng": -73.7784896, "lat": 40.7038345, "zipCode": 11433, "severityType": 0, "year": 2015}, {"date": "2015-05-08", "lng": -73.79379200000001, "lat": 40.704033100000004, "zipCode": 11433, "severityType": 0, "year": 2015}, {"date": "2015-05-07", "lng": -73.7805483, "lat": 40.7084277, "zipCode": 11433, "severityType": 0, "year": 2015}, {"date": "2015-05-06", "lng": -73.7928495, "lat": 40.7044239, "zipCode": 11433, "severityType": 0, "year": 2015}, {"date": "2015-05-06", "lng": -73.78488940000001, "lat": 40.6966251, "zipCode": 11433, "severityType": 1, "year": 2015}, {"date": "2015-05-05", "lng": -73.79357809999999, "lat": 40.6997563, "zipCode": 11433, "severityType": 0, "year": 2015}, {"date": "2015-05-05", "lng": -73.7879315, "lat": 40.7073381, "zipCode": 11433, "severityType": 0, "year": 2015}, {"date": "2015-05-05", "lng": -73.79954129999999, "lat": 40.699160299999996, "zipCode": 11433, "severityType": 0, "year": 2015}, {"date": "2015-05-04", "lng": -73.79550479999999, "lat": 40.694764299999996, "zipCode": 11433, "severityType": 0, "year": 2015}, {"date": "2015-05-04", "lng": -73.7870573, "lat": 40.6908294, "zipCode": 11433, "severityType": 0, "year": 2015}, {"date": "2015-05-04", "lng": -73.7909536, "lat": 40.6925273, "zipCode": 11433, "severityType": 0, "year": 2015}, {"date": "2015-05-04", "lng": -73.78337049999999, "lat": 40.7068328, "zipCode": 11433, "severityType": 0, "year": 2015}, {"date": "2015-05-03", "lng": -73.7891613, "lat": 40.706228700000004, "zipCode": 11433, "severityType": 0, "year": 2015}, {"date": "2015-05-03", "lng": -73.7844078, "lat": 40.703933500000005, "zipCode": 11433, "severityType": 0, "year": 2015}, {"date": "2015-05-03", "lng": -73.7998599, "lat": 40.6963474, "zipCode": 11433, "severityType": 0, "year": 2015}, {"date": "2015-05-03", "lng": -73.7849603, "lat": 40.7003636, "zipCode": 11433, "severityType": 0, "year": 2015}, {"date": "2015-05-03", "lng": -73.7984161, "lat": 40.7027402, "zipCode": 11433, "severityType": 0, "year": 2015}, {"date": "2015-05-02", "lng": -73.8018952, "lat": 40.701969500000004, "zipCode": 11433, "severityType": 0, "year": 2015}, {"date": "2015-05-02", "lng": -73.7805483, "lat": 40.7084277, "zipCode": 11433, "severityType": 0, "year": 2015}, {"date": "2015-05-01", "lng": -73.79405320000001, "lat": 40.69537929999999, "zipCode": 11433, "severityType": 0, "year": 2015}, {"date": "2015-05-01", "lng": -73.7912475, "lat": 40.6965654, "zipCode": 11433, "severityType": 0, "year": 2015}, {"date": "2015-05-01", "lng": -73.7831993, "lat": 40.7006979, "zipCode": 11433, "severityType": 0, "year": 2015}, {"date": "2015-05-01", "lng": -73.7866075, "lat": 40.6961589, "zipCode": 11433, "severityType": 0, "year": 2015}, {"date": "2015-05-01", "lng": -73.78731379999999, "lat": 40.6940605, "zipCode": 11433, "severityType": 0, "year": 2015}, {"date": "2015-04-30", "lng": -73.7881564, "lat": 40.7012671, "zipCode": 11433, "severityType": 0, "year": 2015}, {"date": "2015-04-29", "lng": -73.7960918, "lat": 40.7032933, "zipCode": 11433, "severityType": 1, "year": 2015}, {"date": "2015-04-29", "lng": -73.79557840000001, "lat": 40.7025321, "zipCode": 11433, "severityType": 0, "year": 2015}, {"date": "2015-04-28", "lng": -73.78751740000001, "lat": 40.70371420000001, "zipCode": 11433, "severityType": 0, "year": 2015}, {"date": "2015-04-28", "lng": -73.7916369, "lat": 40.6954408, "zipCode": 11433, "severityType": 1, "year": 2015}, {"date": "2015-04-28", "lng": -73.78884980000001, "lat": 40.7055035, "zipCode": 11433, "severityType": 0, "year": 2015}, {"date": "2015-04-26", "lng": -73.79379200000001, "lat": 40.704033100000004, "zipCode": 11433, "severityType": 0, "year": 2015}, {"date": "2015-04-25", "lng": -73.78146329999998, "lat": 40.694469500000004, "zipCode": 11433, "severityType": 0, "year": 2015}, {"date": "2015-04-25", "lng": -73.78942409999999, "lat": 40.7018376, "zipCode": 11433, "severityType": 0, "year": 2015}, {"date": "2015-04-25", "lng": -73.7896405, "lat": 40.697246, "zipCode": 11433, "severityType": 0, "year": 2015}, {"date": "2015-04-23", "lng": -73.77981679999999, "lat": 40.70492670000001, "zipCode": 11433, "severityType": 0, "year": 2015}, {"date": "2015-04-23", "lng": -73.799184, "lat": 40.6968705, "zipCode": 11433, "severityType": 0, "year": 2015}, {"date": "2015-04-22", "lng": -73.7802385, "lat": 40.6929712, "zipCode": 11433, "severityType": 1, "year": 2015}, {"date": "2015-04-21", "lng": -73.79357809999999, "lat": 40.6997563, "zipCode": 11433, "severityType": 0, "year": 2015}, {"date": "2015-04-21", "lng": -73.79369670000001, "lat": 40.6893758, "zipCode": 11433, "severityType": 0, "year": 2015}, {"date": "2015-04-19", "lng": -73.77826400000001, "lat": 40.697910799999995, "zipCode": 11433, "severityType": 0, "year": 2015}, {"date": "2015-04-18", "lng": -73.7959083, "lat": 40.690170200000004, "zipCode": 11433, "severityType": 0, "year": 2015}, {"date": "2015-04-17", "lng": -73.7825671, "lat": 40.705426, "zipCode": 11433, "severityType": 0, "year": 2015}, {"date": "2015-04-15", "lng": -73.7825671, "lat": 40.705426, "zipCode": 11433, "severityType": 0, "year": 2015}, {"date": "2015-04-15", "lng": -73.7825671, "lat": 40.705426, "zipCode": 11433, "severityType": 0, "year": 2015}, {"date": "2015-04-15", "lng": -73.78884980000001, "lat": 40.7055035, "zipCode": 11433, "severityType": 0, "year": 2015}, {"date": "2015-04-15", "lng": -73.80210109999999, "lat": 40.7006414, "zipCode": 11433, "severityType": 0, "year": 2015}, {"date": "2015-04-15", "lng": -73.7844195, "lat": 40.7047625, "zipCode": 11433, "severityType": 0, "year": 2015}, {"date": "2015-04-14", "lng": -73.7921314, "lat": 40.694115999999994, "zipCode": 11433, "severityType": 0, "year": 2015}, {"date": "2015-04-13", "lng": -73.791937, "lat": 40.703253000000004, "zipCode": 11433, "severityType": 0, "year": 2015}, {"date": "2015-04-13", "lng": -73.79954129999999, "lat": 40.699160299999996, "zipCode": 11433, "severityType": 0, "year": 2015}, {"date": "2015-04-13", "lng": -73.7766316, "lat": 40.6986185, "zipCode": 11433, "severityType": 0, "year": 2015}, {"date": "2015-04-11", "lng": -73.7912475, "lat": 40.6965654, "zipCode": 11433, "severityType": 0, "year": 2015}, {"date": "2015-04-11", "lng": -73.7983005, "lat": 40.6956558, "zipCode": 11433, "severityType": 0, "year": 2015}, {"date": "2015-04-11", "lng": -73.7999209, "lat": 40.7024739, "zipCode": 11433, "severityType": 0, "year": 2015}, {"date": "2015-04-11", "lng": -73.78733740000001, "lat": 40.705868599999995, "zipCode": 11433, "severityType": 0, "year": 2015}, {"date": "2015-04-10", "lng": -73.79239129999999, "lat": 40.70216679999999, "zipCode": 11433, "severityType": 0, "year": 2015}, {"date": "2015-04-09", "lng": -73.79444759999998, "lat": 40.6972848, "zipCode": 11433, "severityType": 0, "year": 2015}, {"date": "2015-04-09", "lng": -73.78516440000001, "lat": 40.7064025, "zipCode": 11433, "severityType": 0, "year": 2015}, {"date": "2015-04-07", "lng": -73.7822786, "lat": 40.705425399999996, "zipCode": 11433, "severityType": 0, "year": 2015}, {"date": "2015-04-07", "lng": -73.7960918, "lat": 40.7032933, "zipCode": 11433, "severityType": 0, "year": 2015}, {"date": "2015-04-06", "lng": -73.78733249999999, "lat": 40.6893148, "zipCode": 11433, "severityType": 0, "year": 2015}, {"date": "2015-04-06", "lng": -73.7865546, "lat": 40.69014779999999, "zipCode": 11433, "severityType": 0, "year": 2015}, {"date": "2015-04-04", "lng": -73.79647729999999, "lat": 40.698693799999994, "zipCode": 11433, "severityType": 0, "year": 2015}, {"date": "2015-04-03", "lng": -73.7839338, "lat": 40.6954952, "zipCode": 11433, "severityType": 0, "year": 2015}, {"date": "2015-04-02", "lng": -73.8010546, "lat": 40.6984191, "zipCode": 11433, "severityType": 0, "year": 2015}, {"date": "2015-04-01", "lng": -73.7834921, "lat": 40.7026994, "zipCode": 11433, "severityType": 0, "year": 2015}, {"date": "2015-03-31", "lng": -73.8024077, "lat": 40.7018524, "zipCode": 11433, "severityType": 0, "year": 2015}, {"date": "2015-03-31", "lng": -73.7839338, "lat": 40.6954952, "zipCode": 11433, "severityType": 0, "year": 2015}, {"date": "2015-03-31", "lng": -73.7874917, "lat": 40.6914231, "zipCode": 11433, "severityType": 0, "year": 2015}, {"date": "2015-03-30", "lng": -73.785848, "lat": 40.7001978, "zipCode": 11433, "severityType": 0, "year": 2015}, {"date": "2015-03-30", "lng": -73.79379200000001, "lat": 40.704033100000004, "zipCode": 11433, "severityType": 0, "year": 2015}, {"date": "2015-03-30", "lng": -73.7925589, "lat": 40.6876885, "zipCode": 11433, "severityType": 0, "year": 2015}, {"date": "2015-03-29", "lng": -73.794641, "lat": 40.70123770000001, "zipCode": 11433, "severityType": 0, "year": 2015}, {"date": "2015-03-29", "lng": -73.79677109999999, "lat": 40.7005141, "zipCode": 11433, "severityType": 0, "year": 2015}, {"date": "2015-03-28", "lng": -73.794641, "lat": 40.70123770000001, "zipCode": 11433, "severityType": 0, "year": 2015}, {"date": "2015-03-28", "lng": -73.787767, "lat": 40.702372499999996, "zipCode": 11433, "severityType": 0, "year": 2015}, {"date": "2015-03-28", "lng": -73.78733740000001, "lat": 40.705868599999995, "zipCode": 11433, "severityType": 0, "year": 2015}, {"date": "2015-03-27", "lng": -73.7999209, "lat": 40.7024739, "zipCode": 11433, "severityType": 0, "year": 2015}, {"date": "2015-03-27", "lng": -73.78751740000001, "lat": 40.70371420000001, "zipCode": 11433, "severityType": 0, "year": 2015}, {"date": "2015-03-27", "lng": -73.78516440000001, "lat": 40.7064025, "zipCode": 11433, "severityType": 0, "year": 2015}, {"date": "2015-03-25", "lng": -73.77478719999999, "lat": 40.695856400000004, "zipCode": 11433, "severityType": 0, "year": 2015}, {"date": "2015-03-25", "lng": -73.7784896, "lat": 40.7038345, "zipCode": 11433, "severityType": 0, "year": 2015}, {"date": "2015-03-24", "lng": -73.79239129999999, "lat": 40.70216679999999, "zipCode": 11433, "severityType": 0, "year": 2015}, {"date": "2015-03-23", "lng": -73.7899943, "lat": 40.7028706, "zipCode": 11433, "severityType": 0, "year": 2015}, {"date": "2015-03-23", "lng": -73.78147779999999, "lat": 40.705454100000004, "zipCode": 11433, "severityType": 0, "year": 2015}, {"date": "2015-03-21", "lng": -73.7854544, "lat": 40.70707, "zipCode": 11433, "severityType": 0, "year": 2015}, {"date": "2015-03-21", "lng": -73.7825671, "lat": 40.705426, "zipCode": 11433, "severityType": 0, "year": 2015}, {"date": "2015-03-20", "lng": -73.78731379999999, "lat": 40.6940605, "zipCode": 11433, "severityType": 0, "year": 2015}, {"date": "2015-03-20", "lng": -73.791937, "lat": 40.703253000000004, "zipCode": 11433, "severityType": 0, "year": 2015}, {"date": "2015-03-19", "lng": -73.7815411, "lat": 40.7026436, "zipCode": 11433, "severityType": 0, "year": 2015}, {"date": "2015-03-19", "lng": -73.8010546, "lat": 40.6984191, "zipCode": 11433, "severityType": 0, "year": 2015}, {"date": "2015-03-18", "lng": -73.78210990000001, "lat": 40.6952365, "zipCode": 11433, "severityType": 0, "year": 2015}, {"date": "2015-03-18", "lng": -73.79405320000001, "lat": 40.69537929999999, "zipCode": 11433, "severityType": 0, "year": 2015}, {"date": "2015-03-17", "lng": -73.77491020000001, "lat": 40.6968283, "zipCode": 11433, "severityType": 0, "year": 2015}, {"date": "2015-03-16", "lng": -73.78487209999999, "lat": 40.697519899999996, "zipCode": 11433, "severityType": 0, "year": 2015}, {"date": "2015-03-16", "lng": -73.7959842, "lat": 40.6924815, "zipCode": 11433, "severityType": 0, "year": 2015}, {"date": "2015-03-15", "lng": -73.7999209, "lat": 40.7024739, "zipCode": 11433, "severityType": 0, "year": 2015}, {"date": "2015-03-13", "lng": -73.79165429999999, "lat": 40.7048554, "zipCode": 11433, "severityType": 0, "year": 2015}, {"date": "2015-03-13", "lng": -73.78210990000001, "lat": 40.6952365, "zipCode": 11433, "severityType": 0, "year": 2015}, {"date": "2015-03-13", "lng": -73.794641, "lat": 40.70123770000001, "zipCode": 11433, "severityType": 0, "year": 2015}, {"date": "2015-03-13", "lng": -73.79165429999999, "lat": 40.7048554, "zipCode": 11433, "severityType": 0, "year": 2015}, {"date": "2015-03-13", "lng": -73.794641, "lat": 40.70123770000001, "zipCode": 11433, "severityType": 0, "year": 2015}, {"date": "2015-03-12", "lng": -73.8024077, "lat": 40.7018524, "zipCode": 11433, "severityType": 0, "year": 2015}, {"date": "2015-03-11", "lng": -73.7862535, "lat": 40.6986066, "zipCode": 11433, "severityType": 0, "year": 2015}, {"date": "2015-03-10", "lng": -73.79357809999999, "lat": 40.6997563, "zipCode": 11433, "severityType": 1, "year": 2015}, {"date": "2015-03-10", "lng": -73.7921314, "lat": 40.694115999999994, "zipCode": 11433, "severityType": 0, "year": 2015}, {"date": "2015-03-10", "lng": -73.7831407, "lat": 40.7020702, "zipCode": 11433, "severityType": 1, "year": 2015}, {"date": "2015-03-10", "lng": -73.78187940000001, "lat": 40.6984529, "zipCode": 11433, "severityType": 0, "year": 2015}, {"date": "2015-03-09", "lng": -73.7910048, "lat": 40.694594200000004, "zipCode": 11433, "severityType": 0, "year": 2015}, {"date": "2015-03-09", "lng": -73.7943413, "lat": 40.693178499999995, "zipCode": 11433, "severityType": 0, "year": 2015}, {"date": "2015-03-06", "lng": -73.7891925, "lat": 40.703204, "zipCode": 11433, "severityType": 0, "year": 2015}, {"date": "2015-03-06", "lng": -73.7986849, "lat": 40.699715999999995, "zipCode": 11433, "severityType": 0, "year": 2015}, {"date": "2015-03-06", "lng": -73.7825671, "lat": 40.705426, "zipCode": 11433, "severityType": 0, "year": 2015}, {"date": "2015-03-06", "lng": -73.79239129999999, "lat": 40.70216679999999, "zipCode": 11433, "severityType": 0, "year": 2015}, {"date": "2015-03-05", "lng": -73.7842729, "lat": 40.7066177, "zipCode": 11433, "severityType": 0, "year": 2015}, {"date": "2015-03-05", "lng": -73.7999209, "lat": 40.7024739, "zipCode": 11433, "severityType": 0, "year": 2015}, {"date": "2015-03-05", "lng": -73.79677109999999, "lat": 40.7005141, "zipCode": 11433, "severityType": 0, "year": 2015}, {"date": "2015-03-05", "lng": -73.79240379999999, "lat": 40.6981513, "zipCode": 11433, "severityType": 0, "year": 2015}, {"date": "2015-03-05", "lng": -73.78330550000001, "lat": 40.707947100000005, "zipCode": 11433, "severityType": 0, "year": 2015}, {"date": "2015-03-05", "lng": -73.78337049999999, "lat": 40.7068328, "zipCode": 11433, "severityType": 0, "year": 2015}, {"date": "2015-03-04", "lng": -73.79954129999999, "lat": 40.699160299999996, "zipCode": 11433, "severityType": 0, "year": 2015}, {"date": "2015-03-04", "lng": -73.7910239, "lat": 40.7057792, "zipCode": 11433, "severityType": 0, "year": 2015}, {"date": "2015-03-03", "lng": -73.7984161, "lat": 40.7027402, "zipCode": 11433, "severityType": 0, "year": 2015}, {"date": "2015-03-03", "lng": -73.8010546, "lat": 40.6984191, "zipCode": 11433, "severityType": 0, "year": 2015}, {"date": "2015-03-03", "lng": -73.8015728, "lat": 40.7012141, "zipCode": 11433, "severityType": 0, "year": 2015}, {"date": "2015-03-02", "lng": -73.7891925, "lat": 40.703204, "zipCode": 11433, "severityType": 0, "year": 2015}, {"date": "2015-03-01", "lng": -73.79357809999999, "lat": 40.6997563, "zipCode": 11433, "severityType": 0, "year": 2015}, {"date": "2015-03-01", "lng": -73.79369670000001, "lat": 40.6893758, "zipCode": 11433, "severityType": 0, "year": 2015}, {"date": "2015-03-01", "lng": -73.78146329999998, "lat": 40.694469500000004, "zipCode": 11433, "severityType": 0, "year": 2015}, {"date": "2015-03-01", "lng": -73.7802385, "lat": 40.6929712, "zipCode": 11433, "severityType": 0, "year": 2015}, {"date": "2015-03-01", "lng": -73.79008759999999, "lat": 40.6949823, "zipCode": 11433, "severityType": 0, "year": 2015}, {"date": "2015-02-28", "lng": -73.7802385, "lat": 40.6929712, "zipCode": 11433, "severityType": 0, "year": 2015}, {"date": "2015-02-27", "lng": -73.7960918, "lat": 40.7032933, "zipCode": 11433, "severityType": 0, "year": 2015}, {"date": "2015-02-27", "lng": -73.79400109999999, "lat": 40.6912346, "zipCode": 11433, "severityType": 0, "year": 2015}, {"date": "2015-02-26", "lng": -73.78516440000001, "lat": 40.7064025, "zipCode": 11433, "severityType": 0, "year": 2015}, {"date": "2015-02-25", "lng": -73.7881046, "lat": 40.6937326, "zipCode": 11433, "severityType": 0, "year": 2015}, {"date": "2015-02-24", "lng": -73.7873116, "lat": 40.70154, "zipCode": 11433, "severityType": 0, "year": 2015}, {"date": "2015-02-24", "lng": -73.794641, "lat": 40.70123770000001, "zipCode": 11433, "severityType": 0, "year": 2015}, {"date": "2015-02-23", "lng": -73.787009, "lat": 40.696909000000005, "zipCode": 11433, "severityType": 0, "year": 2015}, {"date": "2015-02-23", "lng": -73.78146329999998, "lat": 40.694469500000004, "zipCode": 11433, "severityType": 0, "year": 2015}, {"date": "2015-02-22", "lng": -73.7912475, "lat": 40.6965654, "zipCode": 11433, "severityType": 0, "year": 2015}, {"date": "2015-02-22", "lng": -73.7891613, "lat": 40.706228700000004, "zipCode": 11433, "severityType": 0, "year": 2015}, {"date": "2015-02-21", "lng": -73.79444759999998, "lat": 40.6972848, "zipCode": 11433, "severityType": 0, "year": 2015}, {"date": "2015-02-21", "lng": -73.79677109999999, "lat": 40.7005141, "zipCode": 11433, "severityType": 0, "year": 2015}, {"date": "2015-02-21", "lng": -73.7885973, "lat": 40.7021023, "zipCode": 11433, "severityType": 0, "year": 2015}, {"date": "2015-02-20", "lng": -73.78597950000001, "lat": 40.7041862, "zipCode": 11433, "severityType": 0, "year": 2015}, {"date": "2015-02-19", "lng": -73.77792149999999, "lat": 40.703292600000005, "zipCode": 11433, "severityType": 0, "year": 2015}, {"date": "2015-02-18", "lng": -73.7974808, "lat": 40.696002899999996, "zipCode": 11433, "severityType": 0, "year": 2015}, {"date": "2015-02-16", "lng": -73.791937, "lat": 40.703253000000004, "zipCode": 11433, "severityType": 0, "year": 2015}, {"date": "2015-02-16", "lng": -73.7903739, "lat": 40.699124700000006, "zipCode": 11433, "severityType": 0, "year": 2015}, {"date": "2015-02-16", "lng": -73.783825, "lat": 40.7079288, "zipCode": 11433, "severityType": 0, "year": 2015}, {"date": "2015-02-16", "lng": -73.789845, "lat": 40.6930057, "zipCode": 11433, "severityType": 0, "year": 2015}, {"date": "2015-02-15", "lng": -73.794641, "lat": 40.70123770000001, "zipCode": 11433, "severityType": 0, "year": 2015}, {"date": "2015-02-14", "lng": -73.78146329999998, "lat": 40.694469500000004, "zipCode": 11433, "severityType": 0, "year": 2015}, {"date": "2015-02-14", "lng": -73.7833297, "lat": 40.69162120000001, "zipCode": 11433, "severityType": 0, "year": 2015}, {"date": "2015-02-14", "lng": -73.7920324, "lat": 40.6900123, "zipCode": 11433, "severityType": 0, "year": 2015}, {"date": "2015-02-13", "lng": -73.78023979999999, "lat": 40.69914970000001, "zipCode": 11433, "severityType": 0, "year": 2015}, {"date": "2015-02-13", "lng": -73.7890744, "lat": 40.6903857, "zipCode": 11433, "severityType": 0, "year": 2015}, {"date": "2015-02-12", "lng": -73.78893149999999, "lat": 40.693396500000006, "zipCode": 11433, "severityType": 0, "year": 2015}, {"date": "2015-02-12", "lng": -73.7910048, "lat": 40.694594200000004, "zipCode": 11433, "severityType": 0, "year": 2015}, {"date": "2015-02-11", "lng": -73.7808694, "lat": 40.7029113, "zipCode": 11433, "severityType": 0, "year": 2015}, {"date": "2015-02-11", "lng": -73.79677109999999, "lat": 40.7005141, "zipCode": 11433, "severityType": 0, "year": 2015}, {"date": "2015-02-11", "lng": -73.79379200000001, "lat": 40.704033100000004, "zipCode": 11433, "severityType": 0, "year": 2015}, {"date": "2015-02-11", "lng": -73.7815635, "lat": 40.693591299999994, "zipCode": 11433, "severityType": 0, "year": 2015}, {"date": "2015-02-10", "lng": -73.7906838, "lat": 40.6957794, "zipCode": 11433, "severityType": 0, "year": 2015}, {"date": "2015-02-10", "lng": -73.7739552, "lat": 40.6998045, "zipCode": 11433, "severityType": 0, "year": 2015}, {"date": "2015-02-09", "lng": -73.7739552, "lat": 40.6998045, "zipCode": 11433, "severityType": 0, "year": 2015}, {"date": "2015-02-09", "lng": -73.7909536, "lat": 40.6925273, "zipCode": 11433, "severityType": 0, "year": 2015}, {"date": "2015-02-08", "lng": -73.7909536, "lat": 40.6925273, "zipCode": 11433, "severityType": 0, "year": 2015}, {"date": "2015-02-07", "lng": -73.7833297, "lat": 40.69162120000001, "zipCode": 11433, "severityType": 1, "year": 2015}, {"date": "2015-02-07", "lng": -73.7928495, "lat": 40.7044239, "zipCode": 11433, "severityType": 0, "year": 2015}, {"date": "2015-02-06", "lng": -73.79165429999999, "lat": 40.7048554, "zipCode": 11433, "severityType": 0, "year": 2015}, {"date": "2015-02-05", "lng": -73.7825671, "lat": 40.705426, "zipCode": 11433, "severityType": 0, "year": 2015}, {"date": "2015-02-04", "lng": -73.7966612, "lat": 40.6963501, "zipCode": 11433, "severityType": 0, "year": 2015}, {"date": "2015-02-04", "lng": -73.79239129999999, "lat": 40.70216679999999, "zipCode": 11433, "severityType": 0, "year": 2015}, {"date": "2015-02-03", "lng": -73.7978607, "lat": 40.6979935, "zipCode": 11433, "severityType": 0, "year": 2015}, {"date": "2015-02-03", "lng": -73.7897974, "lat": 40.690960700000005, "zipCode": 11433, "severityType": 1, "year": 2015}, {"date": "2015-02-03", "lng": -73.7986849, "lat": 40.699715999999995, "zipCode": 11433, "severityType": 0, "year": 2015}, {"date": "2015-02-03", "lng": -73.79954129999999, "lat": 40.699160299999996, "zipCode": 11433, "severityType": 0, "year": 2015}, {"date": "2015-02-02", "lng": -73.8005321, "lat": 40.6958573, "zipCode": 11433, "severityType": 0, "year": 2015}, {"date": "2015-02-01", "lng": -73.794641, "lat": 40.70123770000001, "zipCode": 11433, "severityType": 0, "year": 2015}, {"date": "2015-02-01", "lng": -73.7991021, "lat": 40.6953141, "zipCode": 11433, "severityType": 0, "year": 2015}, {"date": "2015-01-31", "lng": -73.78942409999999, "lat": 40.7018376, "zipCode": 11433, "severityType": 0, "year": 2015}, {"date": "2015-01-30", "lng": -73.79379200000001, "lat": 40.704033100000004, "zipCode": 11433, "severityType": 0, "year": 2015}, {"date": "2015-01-30", "lng": -73.7825671, "lat": 40.705426, "zipCode": 11433, "severityType": 0, "year": 2015}, {"date": "2015-01-29", "lng": -73.8018952, "lat": 40.701969500000004, "zipCode": 11433, "severityType": 0, "year": 2015}, {"date": "2015-01-28", "lng": -73.782771, "lat": 40.6959953, "zipCode": 11433, "severityType": 0, "year": 2015}, {"date": "2015-01-28", "lng": -73.79954129999999, "lat": 40.699160299999996, "zipCode": 11433, "severityType": 0, "year": 2015}, {"date": "2015-01-27", "lng": -73.7825671, "lat": 40.705426, "zipCode": 11433, "severityType": 0, "year": 2015}, {"date": "2015-01-26", "lng": -73.8018952, "lat": 40.701969500000004, "zipCode": 11433, "severityType": 0, "year": 2015}, {"date": "2015-01-26", "lng": -73.79521319999999, "lat": 40.696962299999996, "zipCode": 11433, "severityType": 0, "year": 2015}, {"date": "2015-01-25", "lng": -73.79255, "lat": 40.6998204, "zipCode": 11433, "severityType": 1, "year": 2015}, {"date": "2015-01-23", "lng": -73.78884980000001, "lat": 40.7055035, "zipCode": 11433, "severityType": 0, "year": 2015}, {"date": "2015-01-23", "lng": -73.800282, "lat": 40.6987196, "zipCode": 11433, "severityType": 0, "year": 2015}, {"date": "2015-01-22", "lng": -73.7817056, "lat": 40.7041864, "zipCode": 11433, "severityType": 0, "year": 2015}, {"date": "2015-01-19", "lng": -73.7839338, "lat": 40.6954952, "zipCode": 11433, "severityType": 0, "year": 2015}, {"date": "2015-01-19", "lng": -73.78733740000001, "lat": 40.705868599999995, "zipCode": 11433, "severityType": 0, "year": 2015}, {"date": "2015-01-19", "lng": -73.79990009999999, "lat": 40.6949861, "zipCode": 11433, "severityType": 0, "year": 2015}, {"date": "2015-01-18", "lng": -73.78778249999999, "lat": 40.6918189, "zipCode": 11433, "severityType": 0, "year": 2015}, {"date": "2015-01-18", "lng": -73.77826400000001, "lat": 40.697910799999995, "zipCode": 11433, "severityType": 0, "year": 2015}, {"date": "2015-01-18", "lng": -73.79379200000001, "lat": 40.704033100000004, "zipCode": 11433, "severityType": 1, "year": 2015}, {"date": "2015-01-17", "lng": -73.78893149999999, "lat": 40.693396500000006, "zipCode": 11433, "severityType": 0, "year": 2015}, {"date": "2015-01-17", "lng": -73.7960918, "lat": 40.7032933, "zipCode": 11433, "severityType": 0, "year": 2015}, {"date": "2015-01-16", "lng": -73.79042779999999, "lat": 40.6969125, "zipCode": 11433, "severityType": 0, "year": 2015}, {"date": "2015-01-16", "lng": -73.7960918, "lat": 40.7032933, "zipCode": 11433, "severityType": 1, "year": 2015}, {"date": "2015-01-16", "lng": -73.7999209, "lat": 40.7024739, "zipCode": 11433, "severityType": 0, "year": 2015}, {"date": "2015-01-16", "lng": -73.7895391, "lat": 40.7008222, "zipCode": 11433, "severityType": 0, "year": 2015}, {"date": "2015-01-15", "lng": -73.79712409999999, "lat": 40.7030344, "zipCode": 11433, "severityType": 0, "year": 2015}, {"date": "2015-01-15", "lng": -73.7960918, "lat": 40.7032933, "zipCode": 11433, "severityType": 0, "year": 2015}, {"date": "2015-01-15", "lng": -73.7825671, "lat": 40.705426, "zipCode": 11433, "severityType": 0, "year": 2015}, {"date": "2015-01-15", "lng": -73.78439350000001, "lat": 40.696091700000004, "zipCode": 11433, "severityType": 0, "year": 2015}, {"date": "2015-01-14", "lng": -73.7839338, "lat": 40.6954952, "zipCode": 11433, "severityType": 0, "year": 2015}, {"date": "2015-01-13", "lng": -73.8018952, "lat": 40.701969500000004, "zipCode": 11433, "severityType": 0, "year": 2015}, {"date": "2015-01-13", "lng": -73.78337049999999, "lat": 40.7068328, "zipCode": 11433, "severityType": 0, "year": 2015}, {"date": "2015-01-12", "lng": -73.7947704, "lat": 40.6908434, "zipCode": 11433, "severityType": 0, "year": 2015}, {"date": "2015-01-11", "lng": -73.7928933, "lat": 40.6937907, "zipCode": 11433, "severityType": 0, "year": 2015}, {"date": "2015-01-10", "lng": -73.79172270000001, "lat": 40.6921994, "zipCode": 11433, "severityType": 0, "year": 2015}, {"date": "2015-01-10", "lng": -73.78733740000001, "lat": 40.705868599999995, "zipCode": 11433, "severityType": 0, "year": 2015}, {"date": "2015-01-09", "lng": -73.7739552, "lat": 40.6998045, "zipCode": 11433, "severityType": 0, "year": 2015}, {"date": "2015-01-09", "lng": -73.7802385, "lat": 40.6929712, "zipCode": 11433, "severityType": 0, "year": 2015}, {"date": "2015-01-09", "lng": -73.7739552, "lat": 40.6998045, "zipCode": 11433, "severityType": 0, "year": 2015}, {"date": "2015-01-08", "lng": -73.78023, "lat": 40.7076064, "zipCode": 11433, "severityType": 0, "year": 2015}, {"date": "2015-01-07", "lng": -73.7891613, "lat": 40.706228700000004, "zipCode": 11433, "severityType": 0, "year": 2015}, {"date": "2015-01-07", "lng": -73.7873536, "lat": 40.6974064, "zipCode": 11433, "severityType": 0, "year": 2015}, {"date": "2015-01-06", "lng": -73.78884980000001, "lat": 40.7055035, "zipCode": 11433, "severityType": 0, "year": 2015}, {"date": "2015-01-06", "lng": -73.787347, "lat": 40.692701899999996, "zipCode": 11433, "severityType": 0, "year": 2015}, {"date": "2015-01-06", "lng": -73.789845, "lat": 40.6930057, "zipCode": 11433, "severityType": 0, "year": 2015}, {"date": "2015-01-06", "lng": -73.79954129999999, "lat": 40.699160299999996, "zipCode": 11433, "severityType": 0, "year": 2015}, {"date": "2015-01-06", "lng": -73.7892715, "lat": 40.6953267, "zipCode": 11433, "severityType": 0, "year": 2015}, {"date": "2015-01-06", "lng": -73.7858777, "lat": 40.697708399999996, "zipCode": 11433, "severityType": 0, "year": 2015}, {"date": "2015-01-06", "lng": -73.7906942, "lat": 40.7050924, "zipCode": 11433, "severityType": 0, "year": 2015}, {"date": "2015-01-05", "lng": -73.79329129999999, "lat": 40.695701799999995, "zipCode": 11433, "severityType": 0, "year": 2015}, {"date": "2015-01-05", "lng": -73.7831407, "lat": 40.7020702, "zipCode": 11433, "severityType": 0, "year": 2015}, {"date": "2015-01-04", "lng": -73.7906942, "lat": 40.7050924, "zipCode": 11433, "severityType": 0, "year": 2015}, {"date": "2015-01-04", "lng": -73.7999209, "lat": 40.7024739, "zipCode": 11433, "severityType": 0, "year": 2015}, {"date": "2015-01-03", "lng": -73.79677109999999, "lat": 40.7005141, "zipCode": 11433, "severityType": 1, "year": 2015}, {"date": "2015-01-03", "lng": -73.79572259999999, "lat": 40.6990136, "zipCode": 11433, "severityType": 1, "year": 2015}, {"date": "2015-01-02", "lng": -73.7815078, "lat": 40.7073014, "zipCode": 11433, "severityType": 0, "year": 2015}, {"date": "2015-01-01", "lng": -73.78893149999999, "lat": 40.693396500000006, "zipCode": 11433, "severityType": 0, "year": 2015}, {"date": "2015-01-01", "lng": -73.789845, "lat": 40.6930057, "zipCode": 11433, "severityType": 0, "year": 2015}, {"date": "2015-01-01", "lng": -73.7874917, "lat": 40.6914231, "zipCode": 11433, "severityType": 0, "year": 2015}]