[{"date": "2018-12-29", "lng": -73.91109499999999, "lat": 40.87465, "zipCode": 10463, "severityType": 0, "year": 2018}, {"date": "2018-12-26", "lng": -73.91051, "lat": 40.87745, "zipCode": 10463, "severityType": 0, "year": 2018}, {"date": "2018-12-23", "lng": -73.90815, "lat": 40.873676, "zipCode": 10463, "severityType": 0, "year": 2018}, {"date": "2018-12-23", "lng": -73.90796999999999, "lat": 40.873642, "zipCode": 10463, "severityType": 0, "year": 2018}, {"date": "2018-12-20", "lng": -73.90886, "lat": 40.874, "zipCode": 10463, "severityType": 1, "year": 2018}, {"date": "2018-12-18", "lng": -73.90796999999999, "lat": 40.873642, "zipCode": 10463, "severityType": 0, "year": 2018}, {"date": "2018-12-14", "lng": -73.91228000000001, "lat": 40.875042, "zipCode": 10463, "severityType": 0, "year": 2018}, {"date": "2018-12-05", "lng": -73.90816, "lat": 40.873695, "zipCode": 10463, "severityType": 0, "year": 2018}, {"date": "2018-12-02", "lng": -73.91141999999999, "lat": 40.876728, "zipCode": 10463, "severityType": 0, "year": 2018}, {"date": "2018-11-26", "lng": -73.91109499999999, "lat": 40.87465, "zipCode": 10463, "severityType": 0, "year": 2018}, {"date": "2018-11-23", "lng": -73.90816, "lat": 40.873695, "zipCode": 10463, "severityType": 0, "year": 2018}, {"date": "2018-11-20", "lng": -73.90836, "lat": 40.875640000000004, "zipCode": 10463, "severityType": 0, "year": 2018}, {"date": "2018-11-15", "lng": -73.90937, "lat": 40.876870000000004, "zipCode": 10463, "severityType": 0, "year": 2018}, {"date": "2018-11-15", "lng": -73.90836, "lat": 40.875640000000004, "zipCode": 10463, "severityType": 0, "year": 2018}, {"date": "2018-11-08", "lng": -73.90937, "lat": 40.874866, "zipCode": 10463, "severityType": 1, "year": 2018}, {"date": "2018-11-04", "lng": -73.90901, "lat": 40.875145, "zipCode": 10463, "severityType": 0, "year": 2018}, {"date": "2018-11-04", "lng": -73.90901, "lat": 40.875145, "zipCode": 10463, "severityType": 0, "year": 2018}, {"date": "2018-11-01", "lng": -73.90796999999999, "lat": 40.873642, "zipCode": 10463, "severityType": 0, "year": 2018}, {"date": "2018-11-01", "lng": -73.91282, "lat": 40.876537, "zipCode": 10463, "severityType": 0, "year": 2018}, {"date": "2018-10-25", "lng": -73.91228000000001, "lat": 40.875042, "zipCode": 10463, "severityType": 0, "year": 2018}, {"date": "2018-10-19", "lng": -73.91211, "lat": 40.87723, "zipCode": 10463, "severityType": 0, "year": 2018}, {"date": "2018-10-18", "lng": -73.90836, "lat": 40.875640000000004, "zipCode": 10463, "severityType": 0, "year": 2018}, {"date": "2018-10-15", "lng": -73.90815, "lat": 40.873676, "zipCode": 10463, "severityType": 0, "year": 2018}, {"date": "2018-10-12", "lng": -73.91202, "lat": 40.877277, "zipCode": 10463, "severityType": 0, "year": 2018}, {"date": "2018-10-03", "lng": -73.90892, "lat": 40.875217, "zipCode": 10463, "severityType": 0, "year": 2018}, {"date": "2018-09-28", "lng": -73.90892, "lat": 40.875217, "zipCode": 10463, "severityType": 0, "year": 2018}, {"date": "2018-09-25", "lng": -73.90879, "lat": 40.877026, "zipCode": 10463, "severityType": 0, "year": 2018}, {"date": "2018-09-16", "lng": -73.91216, "lat": 40.875145, "zipCode": 10463, "severityType": 0, "year": 2018}, {"date": "2018-09-14", "lng": -73.90796999999999, "lat": 40.873642, "zipCode": 10463, "severityType": 0, "year": 2018}, {"date": "2018-09-13", "lng": -73.90886, "lat": 40.874, "zipCode": 10463, "severityType": 0, "year": 2018}, {"date": "2018-09-08", "lng": -73.90796999999999, "lat": 40.873642, "zipCode": 10463, "severityType": 0, "year": 2018}, {"date": "2018-09-08", "lng": -73.90943, "lat": 40.87618, "zipCode": 10463, "severityType": 1, "year": 2018}, {"date": "2018-09-02", "lng": -73.909706, "lat": 40.875717, "zipCode": 10463, "severityType": 0, "year": 2018}, {"date": "2018-08-31", "lng": -73.91083499999999, "lat": 40.87484, "zipCode": 10463, "severityType": 0, "year": 2018}, {"date": "2018-08-19", "lng": -73.90975999999999, "lat": 40.876728, "zipCode": 10463, "severityType": 0, "year": 2018}, {"date": "2018-08-18", "lng": -73.90897, "lat": 40.87406, "zipCode": 10463, "severityType": 0, "year": 2018}, {"date": "2018-08-18", "lng": -73.90836, "lat": 40.875640000000004, "zipCode": 10463, "severityType": 0, "year": 2018}, {"date": "2018-08-17", "lng": -73.90901, "lat": 40.875145, "zipCode": 10463, "severityType": 1, "year": 2018}, {"date": "2018-08-15", "lng": -73.90836, "lat": 40.875640000000004, "zipCode": 10463, "severityType": 0, "year": 2018}, {"date": "2018-08-14", "lng": -73.90857, "lat": 40.875492, "zipCode": 10463, "severityType": 0, "year": 2018}, {"date": "2018-08-04", "lng": -73.90836, "lat": 40.875640000000004, "zipCode": 10463, "severityType": 0, "year": 2018}, {"date": "2018-08-01", "lng": -73.90796999999999, "lat": 40.873642, "zipCode": 10463, "severityType": 0, "year": 2018}, {"date": "2018-07-31", "lng": -73.91246, "lat": 40.875885, "zipCode": 10463, "severityType": 0, "year": 2018}, {"date": "2018-07-30", "lng": -73.91094, "lat": 40.8779, "zipCode": 10463, "severityType": 0, "year": 2018}, {"date": "2018-07-15", "lng": -73.907364, "lat": 40.873515999999995, "zipCode": 10463, "severityType": 0, "year": 2018}, {"date": "2018-07-06", "lng": -73.90796999999999, "lat": 40.873642, "zipCode": 10463, "severityType": 0, "year": 2018}, {"date": "2018-07-02", "lng": -73.90796999999999, "lat": 40.873642, "zipCode": 10463, "severityType": 0, "year": 2018}, {"date": "2018-07-02", "lng": -73.90897, "lat": 40.87406, "zipCode": 10463, "severityType": 0, "year": 2018}, {"date": "2018-06-26", "lng": -73.91171, "lat": 40.874863, "zipCode": 10463, "severityType": 0, "year": 2018}, {"date": "2018-06-23", "lng": -73.90796999999999, "lat": 40.873642, "zipCode": 10463, "severityType": 0, "year": 2018}, {"date": "2018-06-19", "lng": -73.90815, "lat": 40.873676, "zipCode": 10463, "severityType": 0, "year": 2018}, {"date": "2018-06-18", "lng": -73.9088, "lat": 40.875294, "zipCode": 10463, "severityType": 0, "year": 2018}, {"date": "2018-06-12", "lng": -73.91015, "lat": 40.875374, "zipCode": 10463, "severityType": 0, "year": 2018}, {"date": "2018-06-11", "lng": -73.91154499999999, "lat": 40.877613000000004, "zipCode": 10463, "severityType": 0, "year": 2018}, {"date": "2018-06-11", "lng": -73.90816, "lat": 40.873695, "zipCode": 10463, "severityType": 0, "year": 2018}, {"date": "2018-06-09", "lng": -73.91228000000001, "lat": 40.875042, "zipCode": 10463, "severityType": 0, "year": 2018}, {"date": "2018-06-08", "lng": -73.91228000000001, "lat": 40.875042, "zipCode": 10463, "severityType": 0, "year": 2018}, {"date": "2018-06-06", "lng": -73.90836, "lat": 40.875640000000004, "zipCode": 10463, "severityType": 0, "year": 2018}, {"date": "2018-06-02", "lng": -73.90796999999999, "lat": 40.873642, "zipCode": 10463, "severityType": 0, "year": 2018}, {"date": "2018-05-21", "lng": -73.90943, "lat": 40.87618, "zipCode": 10463, "severityType": 0, "year": 2018}, {"date": "2018-05-11", "lng": -73.90836, "lat": 40.875640000000004, "zipCode": 10463, "severityType": 0, "year": 2018}, {"date": "2018-05-09", "lng": -73.909065, "lat": 40.87413, "zipCode": 10463, "severityType": 0, "year": 2018}, {"date": "2018-05-09", "lng": -73.90930999999999, "lat": 40.874886, "zipCode": 10463, "severityType": 0, "year": 2018}, {"date": "2018-05-09", "lng": -73.90886, "lat": 40.874, "zipCode": 10463, "severityType": 0, "year": 2018}, {"date": "2018-05-08", "lng": -73.90999000000001, "lat": 40.877827, "zipCode": 10463, "severityType": 0, "year": 2018}, {"date": "2018-05-07", "lng": -73.91211, "lat": 40.87723, "zipCode": 10463, "severityType": 0, "year": 2018}, {"date": "2018-05-01", "lng": -73.90935, "lat": 40.874336, "zipCode": 10463, "severityType": 0, "year": 2018}, {"date": "2018-05-01", "lng": -73.90905, "lat": 40.87722, "zipCode": 10463, "severityType": 0, "year": 2018}, {"date": "2018-04-28", "lng": -73.909256, "lat": 40.877056, "zipCode": 10463, "severityType": 0, "year": 2018}, {"date": "2018-04-10", "lng": -73.91250600000001, "lat": 40.876872999999996, "zipCode": 10463, "severityType": 0, "year": 2018}, {"date": "2018-03-20", "lng": -73.90815, "lat": 40.873676, "zipCode": 10463, "severityType": 0, "year": 2018}, {"date": "2018-03-20", "lng": -73.90816, "lat": 40.873695, "zipCode": 10463, "severityType": 0, "year": 2018}, {"date": "2018-03-18", "lng": -73.90836, "lat": 40.875640000000004, "zipCode": 10463, "severityType": 0, "year": 2018}, {"date": "2018-03-13", "lng": -73.90815, "lat": 40.873676, "zipCode": 10463, "severityType": 0, "year": 2018}, {"date": "2018-03-13", "lng": -73.90857, "lat": 40.875492, "zipCode": 10463, "severityType": 1, "year": 2018}, {"date": "2018-03-09", "lng": -73.91216, "lat": 40.875145, "zipCode": 10463, "severityType": 0, "year": 2018}, {"date": "2018-03-07", "lng": -73.90796999999999, "lat": 40.873642, "zipCode": 10463, "severityType": 0, "year": 2018}, {"date": "2018-03-04", "lng": -73.90789000000001, "lat": 40.876020000000004, "zipCode": 10463, "severityType": 0, "year": 2018}, {"date": "2018-02-26", "lng": -73.90968000000001, "lat": 40.875763, "zipCode": 10463, "severityType": 0, "year": 2018}, {"date": "2018-02-26", "lng": -73.9088, "lat": 40.875294, "zipCode": 10463, "severityType": 0, "year": 2018}, {"date": "2018-02-14", "lng": -73.90816, "lat": 40.873695, "zipCode": 10463, "severityType": 0, "year": 2018}, {"date": "2018-02-12", "lng": -73.91228000000001, "lat": 40.875042, "zipCode": 10463, "severityType": 0, "year": 2018}, {"date": "2018-01-31", "lng": -73.90942, "lat": 40.8775, "zipCode": 10463, "severityType": 0, "year": 2018}, {"date": "2018-01-29", "lng": -73.91109499999999, "lat": 40.87465, "zipCode": 10463, "severityType": 1, "year": 2018}, {"date": "2018-01-28", "lng": -73.91058000000001, "lat": 40.874424, "zipCode": 10463, "severityType": 0, "year": 2018}, {"date": "2018-01-16", "lng": -73.90796999999999, "lat": 40.873642, "zipCode": 10463, "severityType": 0, "year": 2018}, {"date": "2018-01-14", "lng": -73.91184, "lat": 40.877407, "zipCode": 10463, "severityType": 0, "year": 2018}, {"date": "2018-01-09", "lng": -73.90815, "lat": 40.873676, "zipCode": 10463, "severityType": 0, "year": 2018}, {"date": "2018-01-06", "lng": -73.909706, "lat": 40.875717, "zipCode": 10463, "severityType": 0, "year": 2018}]